Workbook
Name itens_todos: '_ref_itens'!$A$2:$A$999
Name itens_combo: '_ref_itens'!$A$2:$A$1498

Sheet _Leia-me
A1: GASTÃO — PLANILHA-MÃE DE IMPORTAÇÃO
A3: Esta planilha cobre o modelo completo de fichas técnicas: Insumos → Preparos → Fichas.
A4: Funciona para qualquer segmento (hamburgueria, italiano, japonês, eventos, fine dining).
A6: ═══ ORDEM DE PREENCHIMENTO ═══
A7: 1) _Categorias — liste TODAS as categorias que vai usar (insumo, preparo, ficha)
A8: 2) Insumos — ingredientes crus (inclui embalagens)
A9: 3) Preparos — mini-receitas / bases (molhos, massas, fundos, etc)
A10: 4) Fichas — produtos vendidos ao cliente
A11: 5) Composicao_Preparos — o que vai dentro de cada preparo
A12: 6) Composicao_Fichas — o que vai dentro de cada ficha
A14: ═══ DROPDOWNS E FÓRMULAS (NOVO) ═══
A15: • Categoria (Insumos/Preparos/Fichas): dropdown puxa de _Categorias.
... A59: → o importador calcula tudo na ordem certa automaticamente

Sheet _Categorias
A1: Tipo de Item | B1: Categoria | C1: Descrição
A2: insumo | B2: Hortifruti | C2: Frutas, legumes e verduras
A3: insumo | B3: Carnes | C3: Bovinos, suínos, aves, peixes
A4: insumo | B4: Laticínios | C4: Queijos, leite, manteiga, creme
A5: insumo | B5: Mercearia | C5: Secos em geral, farinhas, ovos
A6: insumo | B6: Enlatados | C6: Tomate pelado, atum, milho, etc
A7: insumo | B7: Panificação | C7: Pães, massas prontas
A8: insumo | B8: Bebidas | C8: Refrigerantes, sucos, cervejas
A9: insumo | B9: Descartáveis | C9: Embalagens, guardanapos, talheres
A10: preparo | B10: Molhos Base | C10: Bases reutilizáveis: tomate, béchamel, fundo
A11: preparo | B11: Molhos Finalizadores | C11: Compostos derivados das bases
A12: preparo | B12: Massas | C12: Massas frescas e recheios
... A18: ficha | B18: Sobremesa | C18: Doces e sobremesas da casa

Sheet Insumos
A1: Nome | B1: Categoria | C1: Tipo | D1: Unidade | E1: Preço de Compra | F1: Aproveitamento (%) | G1: Observações
A2: Carne Moída 80/20 | B2: Carnes | C2: insumo_base | D2: kg | E2: 38 | F2: 95 | G2: Perda mínima de gordura
A3: Tomate Pelado Lata | B3: Enlatados | C3: insumo_base | D3: kg | E3: 8 | F3: 100 | G3: Lata de 2,5kg
A4: Cebola | B4: Hortifruti | C4: insumo_base | D4: kg | E4: 4 | F4: 85 | G4: Descasca perde 15%
A5: Alho | B5: Hortifruti | C5: insumo_base | D5: kg | E5: 35 | F5: 80
A6: Azeite Extra Virgem | B6: Mercearia | C6: insumo_base | D6: l | E6: 40 | F6: 100
A7: Queijo Muçarela | B7: Laticínios | C7: insumo_base | D7: kg | E7: 45 | F7: 100
A8: Queijo Parmesão | B8: Laticínios | C8: insumo_direto | D8: kg | E8: 120 | F8: 100 | G8: Ralado na hora direto na ficha
A9: Farinha Tipo 00 | B9: Mercearia | C9: insumo_base | D9: kg | E9: 8 | F9: 100 | G9: Massas italianas
A10: Ovo | B10: Mercearia | C10: insumo_base | D10: un | E10: 0.8 | F10: 100
A11: Manteiga sem sal | B11: Laticínios | C11: insumo_base | D11: kg | E11: 55 | F11: 100
A12: Leite Integral | B12: Laticínios | C12: insumo_base | D12: l | E12: 6.5 | F12: 100
A13: Pão de Hambúrguer | B13: Panificação | C13: insumo_direto | D13: un | E13: 1.8 | F13: 100
A14: Arroz para Sushi | B14: Mercearia | C14: insumo_base | D14: kg | E14: 18 | F14: 100
A15: Salmão Fresco | B15: Carnes | C15: insumo_base | D15: kg | E15: 95 | F15: 60 | G15: Rendimento limpo ~60%
A16: Folha de Nori | B16: Mercearia | C16: insumo_direto | D16: un | E16: 1.2 | F16: 100
A17: Chocolate 70% | B17: Mercearia | C17: insumo_base | D17: kg | E17: 65 | F17: 100
A18: Caixa Delivery | B18: Descartáveis | C18: embalagem | D18: un | E18: 0.85 | F18: 100
A19: Coca-Cola Lata 350ml | B19: Bebidas | C19: insumo_direto | D19: un | E19: 2.8 | F19: 100

Sheet Preparos
A1: Nome | B1: Categoria | C1: Rendimento (qtd) | D1: Rendimento (unidade) | E1: Observações
A2: Molho de Tomate Base | B2: Molhos Base | C2: 2 | D2: kg | E2: Base para ragu, pizza, arrabiata
A3: Molho Branco (Béchamel) | B3: Molhos Base | C3: 1 | D3: kg | E3: Manteiga + farinha + leite
A4: Ragu | B4: Molhos Finalizadores | C4: 3 | D4: kg | E4: Usa Molho de Tomate Base
A5: Molho Rosé | B5: Molhos Finalizadores | C5: 1 | D5: kg | E5: Ragu + Molho Branco, 60/40
A6: Massa de Lasanha | B6: Massas | C6: 1 | D6: kg | E6: Massa fresca ao ovo
A7: Arroz Shari | B7: Bases Sushi | C7: 5 | D7: kg | E7: Arroz temperado pronto para sushi
A8: Smash 80g | B8: Molhos Base | C8: 10 | D8: un | E8: Bolinho 80g prensado

Sheet Fichas
A1: Nome | B1: Categoria | C1: Preço de Venda | D1: Unidade de Venda | E1: Observações
A2: X-Burger Duplo | B2: Lanches | C2: 32 | D2: un
A3: Lasanha à Bolonhesa | B3: Massas | C3: 68 | D3: un | E3: Porção 350g
A4: Pizza Margherita | B4: Pizza | C4: 54 | D4: un | E4: Brotinho
A5: Filé ao Molho Rosé | B5: Massas | C5: 89 | D5: un
A6: Hot Roll Salmão | B6: Sushi | C6: 38 | D6: un | E6: 8 peças
A7: Brigadeiro da Casa | B7: Sobremesa | C7: 12 | D7: un
A8: Combo X-Burger | B8: Lanches | C8: 38 | D8: un | E8: X-Burger Duplo + Coca

Sheet _ref_itens
A1: item
A2: =IFERROR(Insumos!A2,"")
A3: =IFERROR(Insumos!A3,"")
A4: =IFERROR(Insumos!A4,"")
A5: =IFERROR(Insumos!A5,"")
A6: =IFERROR(Insumos!A6,"")
A7: =IFERROR(Insumos!A7,"")
A8: =IFERROR(Insumos!A8,"")
A9: =IFERROR(Insumos!A9,"")
A10: =IFERROR(Insumos!A10,"")
A11: =IFERROR(Insumos!A11,"")
A12: =IFERROR(Insumos!A12,"")
A13: =IFERROR(Insumos!A13,"")
... A500: =IFERROR(Insumos!A500,"")
A501: =IFERROR(Preparos!A2,"")
A502: =IFERROR(Preparos!A3,"")
A503: =IFERROR(Preparos!A4,"")
A504: =IFERROR(Preparos!A5,"")
A505: =IFERROR(Preparos!A6,"")
A506: =IFERROR(Preparos!A7,"")
A507: =IFERROR(Preparos!A8,"")
A508: =IFERROR(Preparos!A9,"")
A509: =IFERROR(Preparos!A10,"")
A510: =IFERROR(Preparos!A11,"")
A511: =IFERROR(Preparos!A12,"")
A512: =IFERROR(Preparos!A13,"")
... A999: =IFERROR(Preparos!A500,"")
A1000: =IFERROR(Fichas!A2,"")
A1001: =IFERROR(Fichas!A3,"")
A1002: =IFERROR(Fichas!A4,"")
A1003: =IFERROR(Fichas!A5,"")
A1004: =IFERROR(Fichas!A6,"")
A1005: =IFERROR(Fichas!A7,"")
A1006: =IFERROR(Fichas!A8,"")
A1007: =IFERROR(Fichas!A9,"")
A1008: =IFERROR(Fichas!A10,"")
A1009: =IFERROR(Fichas!A11,"")
A1010: =IFERROR(Fichas!A12,"")
A1011: =IFERROR(Fichas!A13,"")
... A1498: =IFERROR(Fichas!A500,"")

Sheet Composicao_Preparos
A1: Preparo | B1: Componente (auto) | C1: Item | D1: Quantidade | E1: Unidade (auto)
A2: Molho de Tomate Base | B2: =IF(C2="","",IF(ISNUMBER(MATCH(C2,Insumos!$A:$A,0)),"insumo",IF(ISNUMBER(MATCH(C2,Preparos!$A:$A,0)),"preparo",""))) -> insumo | C2: Tomate Pelado Lata | D2: 2 | E2: =IF(C2="","",IFERROR(VLOOKUP(C2,Insumos!$A:$D,4,FALSE),IFERROR(VLOOKUP(C2,Preparos!$A:$D,4,FALSE),""))) -> kg
A3: Molho de Tomate Base | B3: =IF(C3="","",IF(ISNUMBER(MATCH(C3,Insumos!$A:$A,0)),"insumo",IF(ISNUMBER(MATCH(C3,Preparos!$A:$A,0)),"preparo",""))) -> insumo | C3: Cebola | D3: 0.3 | E3: =IF(C3="","",IFERROR(VLOOKUP(C3,Insumos!$A:$D,4,FALSE),IFERROR(VLOOKUP(C3,Preparos!$A:$D,4,FALSE),""))) -> kg
A4: Molho de Tomate Base | B4: =IF(C4="","",IF(ISNUMBER(MATCH(C4,Insumos!$A:$A,0)),"insumo",IF(ISNUMBER(MATCH(C4,Preparos!$A:$A,0)),"preparo",""))) -> insumo | C4: Alho | D4: 0.05 | E4: =IF(C4="","",IFERROR(VLOOKUP(C4,Insumos!$A:$D,4,FALSE),IFERROR(VLOOKUP(C4,Preparos!$A:$D,4,FALSE),""))) -> kg
A5: Molho de Tomate Base | B5: =IF(C5="","",IF(ISNUMBER(MATCH(C5,Insumos!$A:$A,0)),"insumo",IF(ISNUMBER(MATCH(C5,Preparos!$A:$A,0)),"preparo",""))) -> insumo | C5: Azeite Extra Virgem | D5: 0.1 | E5: =IF(C5="","",IFERROR(VLOOKUP(C5,Insumos!$A:$D,4,FALSE),IFERROR(VLOOKUP(C5,Preparos!$A:$D,4,FALSE),""))) -> l
A6: Molho Branco (Béchamel) | B6: =IF(C6="","",IF(ISNUMBER(MATCH(C6,Insumos!$A:$A,0)),"insumo",IF(ISNUMBER(MATCH(C6,Preparos!$A:$A,0)),"preparo",""))) -> insumo | C6: Manteiga sem sal | D6: 0.08 | E6: =IF(C6="","",IFERROR(VLOOKUP(C6,Insumos!$A:$D,4,FALSE),IFERROR(VLOOKUP(C6,Preparos!$A:$D,4,FALSE),""))) -> kg
A7: Molho Branco (Béchamel) | B7: =IF(C7="","",IF(ISNUMBER(MATCH(C7,Insumos!$A:$A,0)),"insumo",IF(ISNUMBER(MATCH(C7,Preparos!$A:$A,0)),"preparo",""))) -> insumo | C7: Farinha Tipo 00 | D7: 0.08 | E7: =IF(C7="","",IFERROR(VLOOKUP(C7,Insumos!$A:$D,4,FALSE),IFERROR(VLOOKUP(C7,Preparos!$A:$D,4,FALSE),""))) -> kg
A8: Molho Branco (Béchamel) | B8: =IF(C8="","",IF(ISNUMBER(MATCH(C8,Insumos!$A:$A,0)),"insumo",IF(ISNUMBER(MATCH(C8,Preparos!$A:$A,0)),"preparo",""))) -> insumo | C8: Leite Integral | D8: 1 | E8: =IF(C8="","",IFERROR(VLOOKUP(C8,Insumos!$A:$D,4,FALSE),IFERROR(VLOOKUP(C8,Preparos!$A:$D,4,FALSE),""))) -> l
A9: Massa de Lasanha | B9: =IF(C9="","",IF(ISNUMBER(MATCH(C9,Insumos!$A:$A,0)),"insumo",IF(ISNUMBER(MATCH(C9,Preparos!$A:$A,0)),"preparo",""))) -> insumo | C9: Farinha Tipo 00 | D9: 0.7 | E9: =IF(C9="","",IFERROR(VLOOKUP(C9,Insumos!$A:$D,4,FALSE),IFERROR(VLOOKUP(C9,Preparos!$A:$D,4,FALSE),""))) -> kg
A10: Massa de Lasanha | B10: =IF(C10="","",IF(ISNUMBER(MATCH(C10,Insumos!$A:$A,0)),"insumo",IF(ISNUMBER(MATCH(C10,Preparos!$A:$A,0)),"preparo",""))) -> insumo | C10: Ovo | D10: 7 | E10: =IF(C10="","",IFERROR(VLOOKUP(C10,Insumos!$A:$D,4,FALSE),IFERROR(VLOOKUP(C10,Preparos!$A:$D,4,FALSE),""))) -> un
A11: Ragu | B11: =IF(C11="","",IF(ISNUMBER(MATCH(C11,Insumos!$A:$A,0)),"insumo",IF(ISNUMBER(MATCH(C11,Preparos!$A:$A,0)),"preparo",""))) -> preparo | C11: Molho de Tomate Base | D11: 1.5 | E11: =IF(C11="","",IFERROR(VLOOKUP(C11,Insumos!$A:$D,4,FALSE),IFERROR(VLOOKUP(C11,Preparos!$A:$D,4,FALSE),""))) -> kg
A12: Ragu | B12: =IF(C12="","",IF(ISNUMBER(MATCH(C12,Insumos!$A:$A,0)),"insumo",IF(ISNUMBER(MATCH(C12,Preparos!$A:$A,0)),"preparo",""))) -> insumo | C12: Carne Moída 80/20 | D12: 1 | E12: =IF(C12="","",IFERROR(VLOOKUP(C12,Insumos!$A:$D,4,FALSE),IFERROR(VLOOKUP(C12,Preparos!$A:$D,4,FALSE),""))) -> kg
A13: Ragu | B13: =IF(C13="","",IF(ISNUMBER(MATCH(C13,Insumos!$A:$A,0)),"insumo",IF(ISNUMBER(MATCH(C13,Preparos!$A:$A,0)),"preparo",""))) -> insumo | C13: Cebola | D13: 0.2 | E13: =IF(C13="","",IFERROR(VLOOKUP(C13,Insumos!$A:$D,4,FALSE),IFERROR(VLOOKUP(C13,Preparos!$A:$D,4,FALSE),""))) -> kg
... A17: Smash 80g | B17: =IF(C17="","",IF(ISNUMBER(MATCH(C17,Insumos!$A:$A,0)),"insumo",IF(ISNUMBER(MATCH(C17,Preparos!$A:$A,0)),"preparo",""))) -> insumo | C17: Carne Moída 80/20 | D17: 0.8 | E17: =IF(C17="","",IFERROR(VLOOKUP(C17,Insumos!$A:$D,4,FALSE),IFERROR(VLOOKUP(C17,Preparos!$A:$D,4,FALSE),""))) -> kg
B18: =IF(C18="","",IF(ISNUMBER(MATCH(C18,Insumos!$A:$A,0)),"insumo",IF(ISNUMBER(MATCH(C18,Preparos!$A:$A,0)),"preparo",""))) | E18: =IF(C18="","",IFERROR(VLOOKUP(C18,Insumos!$A:$D,4,FALSE),IFERROR(VLOOKUP(C18,Preparos!$A:$D,4,FALSE),"")))
B19: =IF(C19="","",IF(ISNUMBER(MATCH(C19,Insumos!$A:$A,0)),"insumo",IF(ISNUMBER(MATCH(C19,Preparos!$A:$A,0)),"preparo",""))) | E19: =IF(C19="","",IFERROR(VLOOKUP(C19,Insumos!$A:$D,4,FALSE),IFERROR(VLOOKUP(C19,Preparos!$A:$D,4,FALSE),"")))
B20: =IF(C20="","",IF(ISNUMBER(MATCH(C20,Insumos!$A:$A,0)),"insumo",IF(ISNUMBER(MATCH(C20,Preparos!$A:$A,0)),"preparo",""))) | E20: =IF(C20="","",IFERROR(VLOOKUP(C20,Insumos!$A:$D,4,FALSE),IFERROR(VLOOKUP(C20,Preparos!$A:$D,4,FALSE),"")))
B21: =IF(C21="","",IF(ISNUMBER(MATCH(C21,Insumos!$A:$A,0)),"insumo",IF(ISNUMBER(MATCH(C21,Preparos!$A:$A,0)),"preparo",""))) | E21: =IF(C21="","",IFERROR(VLOOKUP(C21,Insumos!$A:$D,4,FALSE),IFERROR(VLOOKUP(C21,Preparos!$A:$D,4,FALSE),"")))
B22: =IF(C22="","",IF(ISNUMBER(MATCH(C22,Insumos!$A:$A,0)),"insumo",IF(ISNUMBER(MATCH(C22,Preparos!$A:$A,0)),"preparo",""))) | E22: =IF(C22="","",IFERROR(VLOOKUP(C22,Insumos!$A:$D,4,FALSE),IFERROR(VLOOKUP(C22,Preparos!$A:$D,4,FALSE),"")))
B23: =IF(C23="","",IF(ISNUMBER(MATCH(C23,Insumos!$A:$A,0)),"insumo",IF(ISNUMBER(MATCH(C23,Preparos!$A:$A,0)),"preparo",""))) | E23: =IF(C23="","",IFERROR(VLOOKUP(C23,Insumos!$A:$D,4,FALSE),IFERROR(VLOOKUP(C23,Preparos!$A:$D,4,FALSE),"")))
B24: =IF(C24="","",IF(ISNUMBER(MATCH(C24,Insumos!$A:$A,0)),"insumo",IF(ISNUMBER(MATCH(C24,Preparos!$A:$A,0)),"preparo",""))) | E24: =IF(C24="","",IFERROR(VLOOKUP(C24,Insumos!$A:$D,4,FALSE),IFERROR(VLOOKUP(C24,Preparos!$A:$D,4,FALSE),"")))
B25: =IF(C25="","",IF(ISNUMBER(MATCH(C25,Insumos!$A:$A,0)),"insumo",IF(ISNUMBER(MATCH(C25,Preparos!$A:$A,0)),"preparo",""))) | E25: =IF(C25="","",IFERROR(VLOOKUP(C25,Insumos!$A:$D,4,FALSE),IFERROR(VLOOKUP(C25,Preparos!$A:$D,4,FALSE),"")))
B26: =IF(C26="","",IF(ISNUMBER(MATCH(C26,Insumos!$A:$A,0)),"insumo",IF(ISNUMBER(MATCH(C26,Preparos!$A:$A,0)),"preparo",""))) | E26: =IF(C26="","",IFERROR(VLOOKUP(C26,Insumos!$A:$D,4,FALSE),IFERROR(VLOOKUP(C26,Preparos!$A:$D,4,FALSE),"")))
B27: =IF(C27="","",IF(ISNUMBER(MATCH(C27,Insumos!$A:$A,0)),"insumo",IF(ISNUMBER(MATCH(C27,Preparos!$A:$A,0)),"preparo",""))) | E27: =IF(C27="","",IFERROR(VLOOKUP(C27,Insumos!$A:$D,4,FALSE),IFERROR(VLOOKUP(C27,Preparos!$A:$D,4,FALSE),"")))
B28: =IF(C28="","",IF(ISNUMBER(MATCH(C28,Insumos!$A:$A,0)),"insumo",IF(ISNUMBER(MATCH(C28,Preparos!$A:$A,0)),"preparo",""))) | E28: =IF(C28="","",IFERROR(VLOOKUP(C28,Insumos!$A:$D,4,FALSE),IFERROR(VLOOKUP(C28,Preparos!$A:$D,4,FALSE),"")))
B29: =IF(C29="","",IF(ISNUMBER(MATCH(C29,Insumos!$A:$A,0)),"insumo",IF(ISNUMBER(MATCH(C29,Preparos!$A:$A,0)),"preparo",""))) | E29: =IF(C29="","",IFERROR(VLOOKUP(C29,Insumos!$A:$D,4,FALSE),IFERROR(VLOOKUP(C29,Preparos!$A:$D,4,FALSE),"")))
... B500: =IF(C500="","",IF(ISNUMBER(MATCH(C500,Insumos!$A:$A,0)),"insumo",IF(ISNUMBER(MATCH(C500,Preparos!$A:$A,0)),"preparo",""))) | E500: =IF(C500="","",IFERROR(VLOOKUP(C500,Insumos!$A:$D,4,FALSE),IFERROR(VLOOKUP(C500,Preparos!$A:$D,4,FALSE),"")))

Sheet Composicao_Fichas
A1: Ficha | B1: Componente (auto) | C1: Item | D1: Quantidade | E1: Unidade (auto)
A2: X-Burger Duplo | B2: =IF(C2="","",IF(ISNUMBER(MATCH(C2,Insumos!$A:$A,0)),"insumo",IF(ISNUMBER(MATCH(C2,Preparos!$A:$A,0)),"preparo",IF(ISNUMBER(MATCH(C2,Fichas!$A:$A,0)),"ficha","")))) -> preparo | C2: Smash 80g | D2: 2 | E2: =IF(C2="","",IFERROR(VLOOKUP(C2,Insumos!$A:$D,4,FALSE),IFERROR(VLOOKUP(C2,Preparos!$A:$D,4,FALSE),IFERROR(VLOOKUP(C2,Fichas!$A:$D,4,FALSE),"")))) -> un
A3: X-Burger Duplo | B3: =IF(C3="","",IF(ISNUMBER(MATCH(C3,Insumos!$A:$A,0)),"insumo",IF(ISNUMBER(MATCH(C3,Preparos!$A:$A,0)),"preparo",IF(ISNUMBER(MATCH(C3,Fichas!$A:$A,0)),"ficha","")))) -> insumo | C3: Pão de Hambúrguer | D3: 1 | E3: =IF(C3="","",IFERROR(VLOOKUP(C3,Insumos!$A:$D,4,FALSE),IFERROR(VLOOKUP(C3,Preparos!$A:$D,4,FALSE),IFERROR(VLOOKUP(C3,Fichas!$A:$D,4,FALSE),"")))) -> un
A4: X-Burger Duplo | B4: =IF(C4="","",IF(ISNUMBER(MATCH(C4,Insumos!$A:$A,0)),"insumo",IF(ISNUMBER(MATCH(C4,Preparos!$A:$A,0)),"preparo",IF(ISNUMBER(MATCH(C4,Fichas!$A:$A,0)),"ficha","")))) -> insumo | C4: Queijo Muçarela | D4: 0.05 | E4: =IF(C4="","",IFERROR(VLOOKUP(C4,Insumos!$A:$D,4,FALSE),IFERROR(VLOOKUP(C4,Preparos!$A:$D,4,FALSE),IFERROR(VLOOKUP(C4,Fichas!$A:$D,4,FALSE),"")))) -> kg
A5: X-Burger Duplo | B5: =IF(C5="","",IF(ISNUMBER(MATCH(C5,Insumos!$A:$A,0)),"insumo",IF(ISNUMBER(MATCH(C5,Preparos!$A:$A,0)),"preparo",IF(ISNUMBER(MATCH(C5,Fichas!$A:$A,0)),"ficha","")))) -> insumo | C5: Caixa Delivery | D5: 1 | E5: =IF(C5="","",IFERROR(VLOOKUP(C5,Insumos!$A:$D,4,FALSE),IFERROR(VLOOKUP(C5,Preparos!$A:$D,4,FALSE),IFERROR(VLOOKUP(C5,Fichas!$A:$D,4,FALSE),"")))) -> un
A6: Lasanha à Bolonhesa | B6: =IF(C6="","",IF(ISNUMBER(MATCH(C6,Insumos!$A:$A,0)),"insumo",IF(ISNUMBER(MATCH(C6,Preparos!$A:$A,0)),"preparo",IF(ISNUMBER(MATCH(C6,Fichas!$A:$A,0)),"ficha","")))) -> preparo | C6: Ragu | D6: 0.4 | E6: =IF(C6="","",IFERROR(VLOOKUP(C6,Insumos!$A:$D,4,FALSE),IFERROR(VLOOKUP(C6,Preparos!$A:$D,4,FALSE),IFERROR(VLOOKUP(C6,Fichas!$A:$D,4,FALSE),"")))) -> kg
A7: Lasanha à Bolonhesa | B7: =IF(C7="","",IF(ISNUMBER(MATCH(C7,Insumos!$A:$A,0)),"insumo",IF(ISNUMBER(MATCH(C7,Preparos!$A:$A,0)),"preparo",IF(ISNUMBER(MATCH(C7,Fichas!$A:$A,0)),"ficha","")))) -> preparo | C7: Massa de Lasanha | D7: 0.2 | E7: =IF(C7="","",IFERROR(VLOOKUP(C7,Insumos!$A:$D,4,FALSE),IFERROR(VLOOKUP(C7,Preparos!$A:$D,4,FALSE),IFERROR(VLOOKUP(C7,Fichas!$A:$D,4,FALSE),"")))) -> kg
A8: Lasanha à Bolonhesa | B8: =IF(C8="","",IF(ISNUMBER(MATCH(C8,Insumos!$A:$A,0)),"insumo",IF(ISNUMBER(MATCH(C8,Preparos!$A:$A,0)),"preparo",IF(ISNUMBER(MATCH(C8,Fichas!$A:$A,0)),"ficha","")))) -> insumo | C8: Queijo Muçarela | D8: 0.15 | E8: =IF(C8="","",IFERROR(VLOOKUP(C8,Insumos!$A:$D,4,FALSE),IFERROR(VLOOKUP(C8,Preparos!$A:$D,4,FALSE),IFERROR(VLOOKUP(C8,Fichas!$A:$D,4,FALSE),"")))) -> kg
A9: Lasanha à Bolonhesa | B9: =IF(C9="","",IF(ISNUMBER(MATCH(C9,Insumos!$A:$A,0)),"insumo",IF(ISNUMBER(MATCH(C9,Preparos!$A:$A,0)),"preparo",IF(ISNUMBER(MATCH(C9,Fichas!$A:$A,0)),"ficha","")))) -> insumo | C9: Queijo Parmesão | D9: 0.03 | E9: =IF(C9="","",IFERROR(VLOOKUP(C9,Insumos!$A:$D,4,FALSE),IFERROR(VLOOKUP(C9,Preparos!$A:$D,4,FALSE),IFERROR(VLOOKUP(C9,Fichas!$A:$D,4,FALSE),"")))) -> kg
A10: Filé ao Molho Rosé | B10: =IF(C10="","",IF(ISNUMBER(MATCH(C10,Insumos!$A:$A,0)),"insumo",IF(ISNUMBER(MATCH(C10,Preparos!$A:$A,0)),"preparo",IF(ISNUMBER(MATCH(C10,Fichas!$A:$A,0)),"ficha","")))) -> preparo | C10: Molho Rosé | D10: 0.15 | E10: =IF(C10="","",IFERROR(VLOOKUP(C10,Insumos!$A:$D,4,FALSE),IFERROR(VLOOKUP(C10,Preparos!$A:$D,4,FALSE),IFERROR(VLOOKUP(C10,Fichas!$A:$D,4,FALSE),"")))) -> kg
A11: Hot Roll Salmão | B11: =IF(C11="","",IF(ISNUMBER(MATCH(C11,Insumos!$A:$A,0)),"insumo",IF(ISNUMBER(MATCH(C11,Preparos!$A:$A,0)),"preparo",IF(ISNUMBER(MATCH(C11,Fichas!$A:$A,0)),"ficha","")))) -> preparo | C11: Arroz Shari | D11: 0.18 | E11: =IF(C11="","",IFERROR(VLOOKUP(C11,Insumos!$A:$D,4,FALSE),IFERROR(VLOOKUP(C11,Preparos!$A:$D,4,FALSE),IFERROR(VLOOKUP(C11,Fichas!$A:$D,4,FALSE),"")))) -> kg
A12: Hot Roll Salmão | B12: =IF(C12="","",IF(ISNUMBER(MATCH(C12,Insumos!$A:$A,0)),"insumo",IF(ISNUMBER(MATCH(C12,Preparos!$A:$A,0)),"preparo",IF(ISNUMBER(MATCH(C12,Fichas!$A:$A,0)),"ficha","")))) -> insumo | C12: Salmão Fresco | D12: 0.08 | E12: =IF(C12="","",IFERROR(VLOOKUP(C12,Insumos!$A:$D,4,FALSE),IFERROR(VLOOKUP(C12,Preparos!$A:$D,4,FALSE),IFERROR(VLOOKUP(C12,Fichas!$A:$D,4,FALSE),"")))) -> kg
A13: Hot Roll Salmão | B13: =IF(C13="","",IF(ISNUMBER(MATCH(C13,Insumos!$A:$A,0)),"insumo",IF(ISNUMBER(MATCH(C13,Preparos!$A:$A,0)),"preparo",IF(ISNUMBER(MATCH(C13,Fichas!$A:$A,0)),"ficha","")))) -> insumo | C13: Folha de Nori | D13: 1 | E13: =IF(C13="","",IFERROR(VLOOKUP(C13,Insumos!$A:$D,4,FALSE),IFERROR(VLOOKUP(C13,Preparos!$A:$D,4,FALSE),IFERROR(VLOOKUP(C13,Fichas!$A:$D,4,FALSE),"")))) -> un
... A16: Combo X-Burger | B16: =IF(C16="","",IF(ISNUMBER(MATCH(C16,Insumos!$A:$A,0)),"insumo",IF(ISNUMBER(MATCH(C16,Preparos!$A:$A,0)),"preparo",IF(ISNUMBER(MATCH(C16,Fichas!$A:$A,0)),"ficha","")))) -> insumo | C16: Coca-Cola Lata 350ml | D16: 1 | E16: =IF(C16="","",IFERROR(VLOOKUP(C16,Insumos!$A:$D,4,FALSE),IFERROR(VLOOKUP(C16,Preparos!$A:$D,4,FALSE),IFERROR(VLOOKUP(C16,Fichas!$A:$D,4,FALSE),"")))) -> un
B17: =IF(C17="","",IF(ISNUMBER(MATCH(C17,Insumos!$A:$A,0)),"insumo",IF(ISNUMBER(MATCH(C17,Preparos!$A:$A,0)),"preparo",IF(ISNUMBER(MATCH(C17,Fichas!$A:$A,0)),"ficha","")))) | E17: =IF(C17="","",IFERROR(VLOOKUP(C17,Insumos!$A:$D,4,FALSE),IFERROR(VLOOKUP(C17,Preparos!$A:$D,4,FALSE),IFERROR(VLOOKUP(C17,Fichas!$A:$D,4,FALSE),""))))
B18: =IF(C18="","",IF(ISNUMBER(MATCH(C18,Insumos!$A:$A,0)),"insumo",IF(ISNUMBER(MATCH(C18,Preparos!$A:$A,0)),"preparo",IF(ISNUMBER(MATCH(C18,Fichas!$A:$A,0)),"ficha","")))) | E18: =IF(C18="","",IFERROR(VLOOKUP(C18,Insumos!$A:$D,4,FALSE),IFERROR(VLOOKUP(C18,Preparos!$A:$D,4,FALSE),IFERROR(VLOOKUP(C18,Fichas!$A:$D,4,FALSE),""))))
B19: =IF(C19="","",IF(ISNUMBER(MATCH(C19,Insumos!$A:$A,0)),"insumo",IF(ISNUMBER(MATCH(C19,Preparos!$A:$A,0)),"preparo",IF(ISNUMBER(MATCH(C19,Fichas!$A:$A,0)),"ficha","")))) | E19: =IF(C19="","",IFERROR(VLOOKUP(C19,Insumos!$A:$D,4,FALSE),IFERROR(VLOOKUP(C19,Preparos!$A:$D,4,FALSE),IFERROR(VLOOKUP(C19,Fichas!$A:$D,4,FALSE),""))))
B20: =IF(C20="","",IF(ISNUMBER(MATCH(C20,Insumos!$A:$A,0)),"insumo",IF(ISNUMBER(MATCH(C20,Preparos!$A:$A,0)),"preparo",IF(ISNUMBER(MATCH(C20,Fichas!$A:$A,0)),"ficha","")))) | E20: =IF(C20="","",IFERROR(VLOOKUP(C20,Insumos!$A:$D,4,FALSE),IFERROR(VLOOKUP(C20,Preparos!$A:$D,4,FALSE),IFERROR(VLOOKUP(C20,Fichas!$A:$D,4,FALSE),""))))
B21: =IF(C21="","",IF(ISNUMBER(MATCH(C21,Insumos!$A:$A,0)),"insumo",IF(ISNUMBER(MATCH(C21,Preparos!$A:$A,0)),"preparo",IF(ISNUMBER(MATCH(C21,Fichas!$A:$A,0)),"ficha","")))) | E21: =IF(C21="","",IFERROR(VLOOKUP(C21,Insumos!$A:$D,4,FALSE),IFERROR(VLOOKUP(C21,Preparos!$A:$D,4,FALSE),IFERROR(VLOOKUP(C21,Fichas!$A:$D,4,FALSE),""))))
B22: =IF(C22="","",IF(ISNUMBER(MATCH(C22,Insumos!$A:$A,0)),"insumo",IF(ISNUMBER(MATCH(C22,Preparos!$A:$A,0)),"preparo",IF(ISNUMBER(MATCH(C22,Fichas!$A:$A,0)),"ficha","")))) | E22: =IF(C22="","",IFERROR(VLOOKUP(C22,Insumos!$A:$D,4,FALSE),IFERROR(VLOOKUP(C22,Preparos!$A:$D,4,FALSE),IFERROR(VLOOKUP(C22,Fichas!$A:$D,4,FALSE),""))))
B23: =IF(C23="","",IF(ISNUMBER(MATCH(C23,Insumos!$A:$A,0)),"insumo",IF(ISNUMBER(MATCH(C23,Preparos!$A:$A,0)),"preparo",IF(ISNUMBER(MATCH(C23,Fichas!$A:$A,0)),"ficha","")))) | E23: =IF(C23="","",IFERROR(VLOOKUP(C23,Insumos!$A:$D,4,FALSE),IFERROR(VLOOKUP(C23,Preparos!$A:$D,4,FALSE),IFERROR(VLOOKUP(C23,Fichas!$A:$D,4,FALSE),""))))
B24: =IF(C24="","",IF(ISNUMBER(MATCH(C24,Insumos!$A:$A,0)),"insumo",IF(ISNUMBER(MATCH(C24,Preparos!$A:$A,0)),"preparo",IF(ISNUMBER(MATCH(C24,Fichas!$A:$A,0)),"ficha","")))) | E24: =IF(C24="","",IFERROR(VLOOKUP(C24,Insumos!$A:$D,4,FALSE),IFERROR(VLOOKUP(C24,Preparos!$A:$D,4,FALSE),IFERROR(VLOOKUP(C24,Fichas!$A:$D,4,FALSE),""))))
B25: =IF(C25="","",IF(ISNUMBER(MATCH(C25,Insumos!$A:$A,0)),"insumo",IF(ISNUMBER(MATCH(C25,Preparos!$A:$A,0)),"preparo",IF(ISNUMBER(MATCH(C25,Fichas!$A:$A,0)),"ficha","")))) | E25: =IF(C25="","",IFERROR(VLOOKUP(C25,Insumos!$A:$D,4,FALSE),IFERROR(VLOOKUP(C25,Preparos!$A:$D,4,FALSE),IFERROR(VLOOKUP(C25,Fichas!$A:$D,4,FALSE),""))))
B26: =IF(C26="","",IF(ISNUMBER(MATCH(C26,Insumos!$A:$A,0)),"insumo",IF(ISNUMBER(MATCH(C26,Preparos!$A:$A,0)),"preparo",IF(ISNUMBER(MATCH(C26,Fichas!$A:$A,0)),"ficha","")))) | E26: =IF(C26="","",IFERROR(VLOOKUP(C26,Insumos!$A:$D,4,FALSE),IFERROR(VLOOKUP(C26,Preparos!$A:$D,4,FALSE),IFERROR(VLOOKUP(C26,Fichas!$A:$D,4,FALSE),""))))
B27: =IF(C27="","",IF(ISNUMBER(MATCH(C27,Insumos!$A:$A,0)),"insumo",IF(ISNUMBER(MATCH(C27,Preparos!$A:$A,0)),"preparo",IF(ISNUMBER(MATCH(C27,Fichas!$A:$A,0)),"ficha","")))) | E27: =IF(C27="","",IFERROR(VLOOKUP(C27,Insumos!$A:$D,4,FALSE),IFERROR(VLOOKUP(C27,Preparos!$A:$D,4,FALSE),IFERROR(VLOOKUP(C27,Fichas!$A:$D,4,FALSE),""))))
B28: =IF(C28="","",IF(ISNUMBER(MATCH(C28,Insumos!$A:$A,0)),"insumo",IF(ISNUMBER(MATCH(C28,Preparos!$A:$A,0)),"preparo",IF(ISNUMBER(MATCH(C28,Fichas!$A:$A,0)),"ficha","")))) | E28: =IF(C28="","",IFERROR(VLOOKUP(C28,Insumos!$A:$D,4,FALSE),IFERROR(VLOOKUP(C28,Preparos!$A:$D,4,FALSE),IFERROR(VLOOKUP(C28,Fichas!$A:$D,4,FALSE),""))))
... B500: =IF(C500="","",IF(ISNUMBER(MATCH(C500,Insumos!$A:$A,0)),"insumo",IF(ISNUMBER(MATCH(C500,Preparos!$A:$A,0)),"preparo",IF(ISNUMBER(MATCH(C500,Fichas!$A:$A,0)),"ficha","")))) | E500: =IF(C500="","",IFERROR(VLOOKUP(C500,Insumos!$A:$D,4,FALSE),IFERROR(VLOOKUP(C500,Preparos!$A:$D,4,FALSE),IFERROR(VLOOKUP(C500,Fichas!$A:$D,4,FALSE),""))))
