Workbook
Name itens_todos: '_ref_itens'!$A$2:$A$999
Name itens_combo: '_ref_itens'!$A$2:$A$1498

Sheet _Leia-me
B1: GASTÃO — PLANILHA-MÃE v3 — Ficha Técnica Padronizada
B3: Esta planilha foi feita pra você cadastrar seus insumos, preparos e fichas técnicas de um jeito padronizado, sem chance de dar errado no sistema.
B4: Funciona pra qualquer restaurante: hamburgueria, italiano, sushi, fine dining, eventos.
B6: 🎨 CORES — O QUE CADA UMA SIGNIFICA
B7: 🟡 AMARELO — você preenche aqui.
B8: 🟢 VERDE — o sistema calcula. Não mexa.
B9: ⚪ CINZA — opcional. Preenche se quiser.
B10: 🔴 VERMELHO — tem erro. Confira a aba _Validação.
B12: 📋 ORDEM DE PREENCHIMENTO
B13: 1️⃣ _Categorias — quais categorias você usa (Hortifruti, Carnes, Bebidas...)
B14: 2️⃣ Insumos — tudo que você compra (matéria-prima, item pronto, embalagem)
B15: 3️⃣ Preparos — mini-receitas que você faz na cozinha (molhos, bases, etc)
... B38: Use a tabela abaixo como referência. Se não sabe, deixa 100%.
B40: INGREDIENTE | C40: APROVEITAMENTO TÍPICO
B41: Bacon cru → frito | C41: 30%
B42: Camarão com casca → limpo | C42: 60%
B43: Carne crua → assada/grelhada | C43: 65-75%
B44: Cebola → descascada | C44: 90%
B45: Tomate fresco → sem casca/semente | C45: 80%
B46: Tomate pelado em lata (peso drenado) | C46: 60%
B47: Filé peixe inteiro → limpo sem espinha | C47: 50-60%
B48: Salmão fresco → limpo | C48: 60%
B49: Abacaxi → descascado | C49: 53%
B50: Manga → descascada/sem caroço | C50: 65%
B51: Item pronto sem perda (ovo, refri, lata) | C51: 100%
B52: Embalagem (caixa, sacola) | C52: 100%
B54: 🍳 INSUMO vs PREPARO vs FICHA
B55: INSUMO — algo que você COMPRA (matéria-prima ou produto pronto)
B56: Ex: tomate pelado em lata, queijo muçarela, pão de hambúrguer, refrigerante
B57: PREPARO — algo que você FAZ na cozinha, usando insumos (e/ou outros preparos)
B58: Ex: molho de tomate base, ragu, massa de lasanha, mix de queijos, hambúrguer moldado
B59: Preparos podem usar OUTROS preparos sem limite. Ex: Molho Rosé usa Ragu (que usa Molho Base).
B60: FICHA — um PRATO do cardápio que o cliente compra
B61: Ex: Lasanha à Bolonhesa, X-Burger, Hot Roll Salmão, Combo Família
B63: 🔁 PREPAROS DENTRO DE PREPAROS
B64: Exemplo: o Aligot (preparo) usa Mix de queijos (outro preparo).
B65: O Mix de queijos vai na aba Preparos normalmente. Na composição do Aligot, escolha Mix de queijos como item.
B66: O sistema calcula o custo em cascata automaticamente.
... B74: Dúvidas? Fale com seu contato Gastão / BPO.

Sheet _Categorias
A1: Tipo de Item | B1: Categoria | C1: Descrição
A2: insumo | B2: Hortifruti | C2: Frutas, legumes e verduras
A3: insumo | B3: Carnes | C3: Bovinos, suínos, aves, peixes
A4: insumo | B4: Laticínios | C4: Queijos, leite, manteiga, creme
A5: insumo | B5: Mercearia | C5: Secos em geral, farinhas, açúcar
A6: insumo | B6: Enlatados | C6: Tomate pelado, atum, milho, etc
A7: insumo | B7: Panificação | C7: Pães, massas prontas
A8: insumo | B8: Bebidas | C8: Refrigerantes, sucos, cervejas, vinhos
A9: insumo | B9: Descartáveis | C9: Embalagens, guardanapos, talheres
A10: preparo | B10: Molhos & Caldos | C10: Bases reutilizáveis
A11: preparo | B11: Bases | C11: Massas, arroz, base de pratos
A12: preparo | B12: Carnes Pré | C12: Carnes pré-preparadas (hambúrguer moldado, etc)
... A18: ficha | B18: Combos | C18: Combos / promoções

Sheet Insumos
A1: Nome | B1: Categoria | C1: Tipo | D1: Embalagem (qtd) | E1: Embalagem (unidade) | F1: Preço Embalagem (R$) | G1: Aproveitamento (%) | H1: Densidade (g/ml) | I1: Unidade Canônica (auto) | J1: Custo / un (auto) | K1: Observações
A2: Carne Moída 80/20 | B2: Carnes | C2: insumo_base | D2: 1000 | E2: g | F2: 38 | G2: 95 | I2: =IF(E2="","",IF(OR(E2="kg",E2="g"),"g",IF(OR(E2="l",E2="ml"),"ml",IF(E2="un","un","")))) -> g | J2: =IFERROR(F2/IF(OR(E2="kg",E2="l"),D2*1000,D2),"") -> 0.038 | K2: Perda mínima de gordura
A3: Tomate Pelado em Lata | B3: Enlatados | C3: insumo_base | D3: 800 | E3: g | F3: 14.8 | G3: 60 | I3: =IF(E3="","",IF(OR(E3="kg",E3="g"),"g",IF(OR(E3="l",E3="ml"),"ml",IF(E3="un","un","")))) -> g | J3: =IFERROR(F3/IF(OR(E3="kg",E3="l"),D3*1000,D3),"") -> 0.0185 | K3: Lata 800g, peso drenado 60%
A4: Cebola | B4: Hortifruti | C4: insumo_base | D4: 1000 | E4: g | F4: 4 | G4: 90 | I4: =IF(E4="","",IF(OR(E4="kg",E4="g"),"g",IF(OR(E4="l",E4="ml"),"ml",IF(E4="un","un","")))) -> g | J4: =IFERROR(F4/IF(OR(E4="kg",E4="l"),D4*1000,D4),"") -> 0.004 | K4: Perde 10% ao descascar
A5: Alho | B5: Hortifruti | C5: insumo_base | D5: 1000 | E5: g | F5: 35 | G5: 80 | I5: =IF(E5="","",IF(OR(E5="kg",E5="g"),"g",IF(OR(E5="l",E5="ml"),"ml",IF(E5="un","un","")))) -> g | J5: =IFERROR(F5/IF(OR(E5="kg",E5="l"),D5*1000,D5),"") -> 0.035
A6: Azeite Extra Virgem | B6: Mercearia | C6: insumo_base | D6: 750 | E6: ml | F6: 30 | G6: 100 | H6: 0.92 | I6: =IF(E6="","",IF(OR(E6="kg",E6="g"),"g",IF(OR(E6="l",E6="ml"),"ml",IF(E6="un","un","")))) -> ml | J6: =IFERROR(F6/IF(OR(E6="kg",E6="l"),D6*1000,D6),"") -> 0.04 | K6: Garrafa 750ml
A7: Queijo Muçarela | B7: Laticínios | C7: insumo_base | D7: 1000 | E7: g | F7: 45 | G7: 100 | I7: =IF(E7="","",IF(OR(E7="kg",E7="g"),"g",IF(OR(E7="l",E7="ml"),"ml",IF(E7="un","un","")))) -> g | J7: =IFERROR(F7/IF(OR(E7="kg",E7="l"),D7*1000,D7),"") -> 0.045
A8: Queijo Parmesão | B8: Laticínios | C8: insumo_direto | D8: 1000 | E8: g | F8: 120 | G8: 100 | I8: =IF(E8="","",IF(OR(E8="kg",E8="g"),"g",IF(OR(E8="l",E8="ml"),"ml",IF(E8="un","un","")))) -> g | J8: =IFERROR(F8/IF(OR(E8="kg",E8="l"),D8*1000,D8),"") -> 0.12 | K8: Ralado na hora direto na ficha
A9: Farinha Tipo 00 | B9: Mercearia | C9: insumo_base | D9: 1000 | E9: g | F9: 8 | G9: 100 | I9: =IF(E9="","",IF(OR(E9="kg",E9="g"),"g",IF(OR(E9="l",E9="ml"),"ml",IF(E9="un","un","")))) -> g | J9: =IFERROR(F9/IF(OR(E9="kg",E9="l"),D9*1000,D9),"") -> 0.008 | K9: Massas italianas
A10: Ovo | B10: Mercearia | C10: insumo_base | D10: 1 | E10: un | F10: 0.8 | G10: 100 | I10: =IF(E10="","",IF(OR(E10="kg",E10="g"),"g",IF(OR(E10="l",E10="ml"),"ml",IF(E10="un","un","")))) -> un | J10: =IFERROR(F10/IF(OR(E10="kg",E10="l"),D10*1000,D10),"") -> 0.8 | K10: ~50g por unidade
A11: Manteiga sem sal | B11: Laticínios | C11: insumo_base | D11: 200 | E11: g | F11: 11 | G11: 100 | I11: =IF(E11="","",IF(OR(E11="kg",E11="g"),"g",IF(OR(E11="l",E11="ml"),"ml",IF(E11="un","un","")))) -> g | J11: =IFERROR(F11/IF(OR(E11="kg",E11="l"),D11*1000,D11),"") -> 0.055 | K11: Tablete 200g
A12: Leite Integral | B12: Laticínios | C12: insumo_base | D12: 1000 | E12: ml | F12: 6.5 | G12: 100 | H12: 1.03 | I12: =IF(E12="","",IF(OR(E12="kg",E12="g"),"g",IF(OR(E12="l",E12="ml"),"ml",IF(E12="un","un","")))) -> ml | J12: =IFERROR(F12/IF(OR(E12="kg",E12="l"),D12*1000,D12),"") -> 0.0065 | K12: Caixa 1L
A13: Pão de Hambúrguer | B13: Panificação | C13: insumo_direto | D13: 1 | E13: un | F13: 1.8 | G13: 100 | I13: =IF(E13="","",IF(OR(E13="kg",E13="g"),"g",IF(OR(E13="l",E13="ml"),"ml",IF(E13="un","un","")))) -> un | J13: =IFERROR(F13/IF(OR(E13="kg",E13="l"),D13*1000,D13),"") -> 1.8
A14: Bacon Cru | B14: Carnes | C14: insumo_base | D14: 1000 | E14: g | F14: 43 | G14: 30 | I14: =IF(E14="","",IF(OR(E14="kg",E14="g"),"g",IF(OR(E14="l",E14="ml"),"ml",IF(E14="un","un","")))) -> g | J14: =IFERROR(F14/IF(OR(E14="kg",E14="l"),D14*1000,D14),"") -> 0.043 | K14: Frito rende 30%
A15: Salmão Fresco | B15: Carnes | C15: insumo_base | D15: 1000 | E15: g | F15: 95 | G15: 60 | I15: =IF(E15="","",IF(OR(E15="kg",E15="g"),"g",IF(OR(E15="l",E15="ml"),"ml",IF(E15="un","un","")))) -> g | J15: =IFERROR(F15/IF(OR(E15="kg",E15="l"),D15*1000,D15),"") -> 0.095 | K15: Limpo rende 60%
A16: Camarão Cru c/ casca | B16: Carnes | C16: insumo_base | D16: 1000 | E16: g | F16: 60 | G16: 60 | I16: =IF(E16="","",IF(OR(E16="kg",E16="g"),"g",IF(OR(E16="l",E16="ml"),"ml",IF(E16="un","un","")))) -> g | J16: =IFERROR(F16/IF(OR(E16="kg",E16="l"),D16*1000,D16),"") -> 0.06 | K16: Limpo rende 60%
A17: Coca-Cola Lata 350ml | B17: Bebidas | C17: insumo_direto | D17: 1 | E17: un | F17: 2.8 | G17: 100 | I17: =IF(E17="","",IF(OR(E17="kg",E17="g"),"g",IF(OR(E17="l",E17="ml"),"ml",IF(E17="un","un","")))) -> un | J17: =IFERROR(F17/IF(OR(E17="kg",E17="l"),D17*1000,D17),"") -> 2.8
A18: Caixa Delivery | B18: Descartáveis | C18: embalagem | D18: 1 | E18: un | F18: 0.85 | G18: 100 | I18: =IF(E18="","",IF(OR(E18="kg",E18="g"),"g",IF(OR(E18="l",E18="ml"),"ml",IF(E18="un","un","")))) -> un | J18: =IFERROR(F18/IF(OR(E18="kg",E18="l"),D18*1000,D18),"") -> 0.85
I19: =IF(E19="","",IF(OR(E19="kg",E19="g"),"g",IF(OR(E19="l",E19="ml"),"ml",IF(E19="un","un","")))) | J19: =IFERROR(F19/IF(OR(E19="kg",E19="l"),D19*1000,D19),"")
I20: =IF(E20="","",IF(OR(E20="kg",E20="g"),"g",IF(OR(E20="l",E20="ml"),"ml",IF(E20="un","un","")))) | J20: =IFERROR(F20/IF(OR(E20="kg",E20="l"),D20*1000,D20),"")
I21: =IF(E21="","",IF(OR(E21="kg",E21="g"),"g",IF(OR(E21="l",E21="ml"),"ml",IF(E21="un","un","")))) | J21: =IFERROR(F21/IF(OR(E21="kg",E21="l"),D21*1000,D21),"")
I22: =IF(E22="","",IF(OR(E22="kg",E22="g"),"g",IF(OR(E22="l",E22="ml"),"ml",IF(E22="un","un","")))) | J22: =IFERROR(F22/IF(OR(E22="kg",E22="l"),D22*1000,D22),"")
I23: =IF(E23="","",IF(OR(E23="kg",E23="g"),"g",IF(OR(E23="l",E23="ml"),"ml",IF(E23="un","un","")))) | J23: =IFERROR(F23/IF(OR(E23="kg",E23="l"),D23*1000,D23),"")
I24: =IF(E24="","",IF(OR(E24="kg",E24="g"),"g",IF(OR(E24="l",E24="ml"),"ml",IF(E24="un","un","")))) | J24: =IFERROR(F24/IF(OR(E24="kg",E24="l"),D24*1000,D24),"")
I25: =IF(E25="","",IF(OR(E25="kg",E25="g"),"g",IF(OR(E25="l",E25="ml"),"ml",IF(E25="un","un","")))) | J25: =IFERROR(F25/IF(OR(E25="kg",E25="l"),D25*1000,D25),"")
I26: =IF(E26="","",IF(OR(E26="kg",E26="g"),"g",IF(OR(E26="l",E26="ml"),"ml",IF(E26="un","un","")))) | J26: =IFERROR(F26/IF(OR(E26="kg",E26="l"),D26*1000,D26),"")
I27: =IF(E27="","",IF(OR(E27="kg",E27="g"),"g",IF(OR(E27="l",E27="ml"),"ml",IF(E27="un","un","")))) | J27: =IFERROR(F27/IF(OR(E27="kg",E27="l"),D27*1000,D27),"")
I28: =IF(E28="","",IF(OR(E28="kg",E28="g"),"g",IF(OR(E28="l",E28="ml"),"ml",IF(E28="un","un","")))) | J28: =IFERROR(F28/IF(OR(E28="kg",E28="l"),D28*1000,D28),"")
I29: =IF(E29="","",IF(OR(E29="kg",E29="g"),"g",IF(OR(E29="l",E29="ml"),"ml",IF(E29="un","un","")))) | J29: =IFERROR(F29/IF(OR(E29="kg",E29="l"),D29*1000,D29),"")
I30: =IF(E30="","",IF(OR(E30="kg",E30="g"),"g",IF(OR(E30="l",E30="ml"),"ml",IF(E30="un","un","")))) | J30: =IFERROR(F30/IF(OR(E30="kg",E30="l"),D30*1000,D30),"")
... I500: =IF(E500="","",IF(OR(E500="kg",E500="g"),"g",IF(OR(E500="l",E500="ml"),"ml",IF(E500="un","un","")))) | J500: =IFERROR(F500/IF(OR(E500="kg",E500="l"),D500*1000,D500),"")

Sheet Preparos
A1: Nome | B1: Categoria | C1: Rendimento (qtd) | D1: Rendimento (unidade) | E1: Custo Total (auto) | F1: Custo / un (auto) | G1: Procedimento
A2: Molho de Tomate Base | B2: Molhos & Caldos | C2: 2400 | D2: g | E2: =IFERROR(SUMIFS(Composicao_Preparos!H:H,Composicao_Preparos!A:A,A2),0) | F2: =IF(C2>0,IFERROR(E2/C2,""),"") | G2: Refogar tomate com cebola e alho, cozinhar 40min
A3: Ragu | B3: Molhos & Caldos | C3: 3500 | D3: g | E3: =IFERROR(SUMIFS(Composicao_Preparos!H:H,Composicao_Preparos!A:A,A3),0) | F3: =IF(C3>0,IFERROR(E3/C3,""),"") | G3: Carne moída + Molho de Tomate Base
A4: Hambúrguer Moldado 80g | B4: Carnes Pré | C4: 1 | D4: un | E4: =IFERROR(SUMIFS(Composicao_Preparos!H:H,Composicao_Preparos!A:A,A4),0) | F4: =IF(C4>0,IFERROR(E4/C4,""),"") | G4: Bolinho 80g prensado, 1 unidade
A5: Massa de Lasanha | B5: Bases | C5: 1000 | D5: g | E5: =IFERROR(SUMIFS(Composicao_Preparos!H:H,Composicao_Preparos!A:A,A5),0) | F5: =IF(C5>0,IFERROR(E5/C5,""),"") | G5: Massa fresca ao ovo
E6: =IFERROR(SUMIFS(Composicao_Preparos!H:H,Composicao_Preparos!A:A,A6),0) | F6: =IF(C6>0,IFERROR(E6/C6,""),"")
E7: =IFERROR(SUMIFS(Composicao_Preparos!H:H,Composicao_Preparos!A:A,A7),0) | F7: =IF(C7>0,IFERROR(E7/C7,""),"")
E8: =IFERROR(SUMIFS(Composicao_Preparos!H:H,Composicao_Preparos!A:A,A8),0) | F8: =IF(C8>0,IFERROR(E8/C8,""),"")
E9: =IFERROR(SUMIFS(Composicao_Preparos!H:H,Composicao_Preparos!A:A,A9),0) | F9: =IF(C9>0,IFERROR(E9/C9,""),"")
E10: =IFERROR(SUMIFS(Composicao_Preparos!H:H,Composicao_Preparos!A:A,A10),0) | F10: =IF(C10>0,IFERROR(E10/C10,""),"")
E11: =IFERROR(SUMIFS(Composicao_Preparos!H:H,Composicao_Preparos!A:A,A11),0) | F11: =IF(C11>0,IFERROR(E11/C11,""),"")
E12: =IFERROR(SUMIFS(Composicao_Preparos!H:H,Composicao_Preparos!A:A,A12),0) | F12: =IF(C12>0,IFERROR(E12/C12,""),"")
E13: =IFERROR(SUMIFS(Composicao_Preparos!H:H,Composicao_Preparos!A:A,A13),0) | F13: =IF(C13>0,IFERROR(E13/C13,""),"")
E14: =IFERROR(SUMIFS(Composicao_Preparos!H:H,Composicao_Preparos!A:A,A14),0) | F14: =IF(C14>0,IFERROR(E14/C14,""),"")
E15: =IFERROR(SUMIFS(Composicao_Preparos!H:H,Composicao_Preparos!A:A,A15),0) | F15: =IF(C15>0,IFERROR(E15/C15,""),"")
E16: =IFERROR(SUMIFS(Composicao_Preparos!H:H,Composicao_Preparos!A:A,A16),0) | F16: =IF(C16>0,IFERROR(E16/C16,""),"")
E17: =IFERROR(SUMIFS(Composicao_Preparos!H:H,Composicao_Preparos!A:A,A17),0) | F17: =IF(C17>0,IFERROR(E17/C17,""),"")
... E500: =IFERROR(SUMIFS(Composicao_Preparos!H:H,Composicao_Preparos!A:A,A500),0) | F500: =IF(C500>0,IFERROR(E500/C500,""),"")

Sheet Fichas
A1: Nome | B1: Categoria | C1: Preço de Venda (R$) | D1: Custo Total (auto) | E1: CMV % (auto) | F1: Observações
A2: X-Burger Duplo | B2: Pratos Principais | C2: 32 | D2: =IFERROR(SUMIFS(Composicao_Fichas!H:H,Composicao_Fichas!A:A,A2),0) | E2: =IF(C2>0,IFERROR(D2/C2,""),"")
A3: Lasanha à Bolonhesa | B3: Pratos Principais | C3: 68 | D3: =IFERROR(SUMIFS(Composicao_Fichas!H:H,Composicao_Fichas!A:A,A3),0) | E3: =IF(C3>0,IFERROR(D3/C3,""),"") | F3: Porção 350g
A4: Salmão Grelhado | B4: Pratos Principais | C4: 89 | D4: =IFERROR(SUMIFS(Composicao_Fichas!H:H,Composicao_Fichas!A:A,A4),0) | E4: =IF(C4>0,IFERROR(D4/C4,""),"")
D5: =IFERROR(SUMIFS(Composicao_Fichas!H:H,Composicao_Fichas!A:A,A5),0) | E5: =IF(C5>0,IFERROR(D5/C5,""),"")
D6: =IFERROR(SUMIFS(Composicao_Fichas!H:H,Composicao_Fichas!A:A,A6),0) | E6: =IF(C6>0,IFERROR(D6/C6,""),"")
D7: =IFERROR(SUMIFS(Composicao_Fichas!H:H,Composicao_Fichas!A:A,A7),0) | E7: =IF(C7>0,IFERROR(D7/C7,""),"")
D8: =IFERROR(SUMIFS(Composicao_Fichas!H:H,Composicao_Fichas!A:A,A8),0) | E8: =IF(C8>0,IFERROR(D8/C8,""),"")
D9: =IFERROR(SUMIFS(Composicao_Fichas!H:H,Composicao_Fichas!A:A,A9),0) | E9: =IF(C9>0,IFERROR(D9/C9,""),"")
D10: =IFERROR(SUMIFS(Composicao_Fichas!H:H,Composicao_Fichas!A:A,A10),0) | E10: =IF(C10>0,IFERROR(D10/C10,""),"")
D11: =IFERROR(SUMIFS(Composicao_Fichas!H:H,Composicao_Fichas!A:A,A11),0) | E11: =IF(C11>0,IFERROR(D11/C11,""),"")
D12: =IFERROR(SUMIFS(Composicao_Fichas!H:H,Composicao_Fichas!A:A,A12),0) | E12: =IF(C12>0,IFERROR(D12/C12,""),"")
D13: =IFERROR(SUMIFS(Composicao_Fichas!H:H,Composicao_Fichas!A:A,A13),0) | E13: =IF(C13>0,IFERROR(D13/C13,""),"")
D14: =IFERROR(SUMIFS(Composicao_Fichas!H:H,Composicao_Fichas!A:A,A14),0) | E14: =IF(C14>0,IFERROR(D14/C14,""),"")
D15: =IFERROR(SUMIFS(Composicao_Fichas!H:H,Composicao_Fichas!A:A,A15),0) | E15: =IF(C15>0,IFERROR(D15/C15,""),"")
D16: =IFERROR(SUMIFS(Composicao_Fichas!H:H,Composicao_Fichas!A:A,A16),0) | E16: =IF(C16>0,IFERROR(D16/C16,""),"")
... D500: =IFERROR(SUMIFS(Composicao_Fichas!H:H,Composicao_Fichas!A:A,A500),0) | E500: =IF(C500>0,IFERROR(D500/C500,""),"")

Sheet _ref_itens
A1: item
A2: =IFERROR(Insumos!A2,"")
A3: =IFERROR(Insumos!A3,"")
A4: =IFERROR(Insumos!A4,"")
A5: =IFERROR(Insumos!A5,"")
A6: =IFERROR(Insumos!A6,"")
A7: =IFERROR(Insumos!A7,"")
A8: =IFERROR(Insumos!A8,"")
A9: =IFERROR(Insumos!A9,"")
A10: =IFERROR(Insumos!A10,"")
A11: =IFERROR(Insumos!A11,"")
A12: =IFERROR(Insumos!A12,"")
A13: =IFERROR(Insumos!A13,"")
... A500: =IFERROR(Insumos!A500,"")
A501: =IFERROR(Preparos!A2,"")
A502: =IFERROR(Preparos!A3,"")
A503: =IFERROR(Preparos!A4,"")
A504: =IFERROR(Preparos!A5,"")
A505: =IFERROR(Preparos!A6,"")
A506: =IFERROR(Preparos!A7,"")
A507: =IFERROR(Preparos!A8,"")
A508: =IFERROR(Preparos!A9,"")
A509: =IFERROR(Preparos!A10,"")
A510: =IFERROR(Preparos!A11,"")
A511: =IFERROR(Preparos!A12,"")
A512: =IFERROR(Preparos!A13,"")
... A999: =IFERROR(Preparos!A500,"")
A1000: =IFERROR(Fichas!A2,"")
A1001: =IFERROR(Fichas!A3,"")
A1002: =IFERROR(Fichas!A4,"")
A1003: =IFERROR(Fichas!A5,"")
A1004: =IFERROR(Fichas!A6,"")
A1005: =IFERROR(Fichas!A7,"")
A1006: =IFERROR(Fichas!A8,"")
A1007: =IFERROR(Fichas!A9,"")
A1008: =IFERROR(Fichas!A10,"")
A1009: =IFERROR(Fichas!A11,"")
A1010: =IFERROR(Fichas!A12,"")
A1011: =IFERROR(Fichas!A13,"")
... A1498: =IFERROR(Fichas!A500,"")

Sheet Composicao_Preparos
A1: Preparo | B1: Componente (auto) | C1: Item | D1: Quantidade | E1: Unidade (auto) | F1: Aprov% (auto) | G1: Custo/un (auto) | H1: Custo Linha (auto) | I1: Notas
A2: Molho de Tomate Base | B2: =IF(C2="","",IF(ISNUMBER(MATCH(C2,Insumos!$A:$A,0)),"insumo",IF(ISNUMBER(MATCH(C2,Preparos!$A:$A,0)),"preparo",""))) | C2: Tomate Pelado em Lata | D2: 2000 | E2: =IF(C2="","",IFERROR(VLOOKUP(C2,Insumos!$A:$I,9,FALSE),IFERROR(VLOOKUP(C2,Preparos!$A:$D,4,FALSE),""))) | F2: =IF(C2="","",IFERROR(VLOOKUP(C2,Insumos!$A:$G,7,FALSE),100)) | G2: =IF(C2="","",IFERROR(VLOOKUP(C2,Insumos!$A:$J,10,FALSE),IFERROR(VLOOKUP(C2,Preparos!$A:$F,6,FALSE),0))) | H2: =IF(OR(D2="",G2="",F2=0),"",D2*G2*(100/F2))
A3: Molho de Tomate Base | B3: =IF(C3="","",IF(ISNUMBER(MATCH(C3,Insumos!$A:$A,0)),"insumo",IF(ISNUMBER(MATCH(C3,Preparos!$A:$A,0)),"preparo",""))) | C3: Cebola | D3: 300 | E3: =IF(C3="","",IFERROR(VLOOKUP(C3,Insumos!$A:$I,9,FALSE),IFERROR(VLOOKUP(C3,Preparos!$A:$D,4,FALSE),""))) | F3: =IF(C3="","",IFERROR(VLOOKUP(C3,Insumos!$A:$G,7,FALSE),100)) | G3: =IF(C3="","",IFERROR(VLOOKUP(C3,Insumos!$A:$J,10,FALSE),IFERROR(VLOOKUP(C3,Preparos!$A:$F,6,FALSE),0))) | H3: =IF(OR(D3="",G3="",F3=0),"",D3*G3*(100/F3))
A4: Molho de Tomate Base | B4: =IF(C4="","",IF(ISNUMBER(MATCH(C4,Insumos!$A:$A,0)),"insumo",IF(ISNUMBER(MATCH(C4,Preparos!$A:$A,0)),"preparo",""))) | C4: Alho | D4: 50 | E4: =IF(C4="","",IFERROR(VLOOKUP(C4,Insumos!$A:$I,9,FALSE),IFERROR(VLOOKUP(C4,Preparos!$A:$D,4,FALSE),""))) | F4: =IF(C4="","",IFERROR(VLOOKUP(C4,Insumos!$A:$G,7,FALSE),100)) | G4: =IF(C4="","",IFERROR(VLOOKUP(C4,Insumos!$A:$J,10,FALSE),IFERROR(VLOOKUP(C4,Preparos!$A:$F,6,FALSE),0))) | H4: =IF(OR(D4="",G4="",F4=0),"",D4*G4*(100/F4))
A5: Molho de Tomate Base | B5: =IF(C5="","",IF(ISNUMBER(MATCH(C5,Insumos!$A:$A,0)),"insumo",IF(ISNUMBER(MATCH(C5,Preparos!$A:$A,0)),"preparo",""))) | C5: Azeite Extra Virgem | D5: 100 | E5: =IF(C5="","",IFERROR(VLOOKUP(C5,Insumos!$A:$I,9,FALSE),IFERROR(VLOOKUP(C5,Preparos!$A:$D,4,FALSE),""))) | F5: =IF(C5="","",IFERROR(VLOOKUP(C5,Insumos!$A:$G,7,FALSE),100)) | G5: =IF(C5="","",IFERROR(VLOOKUP(C5,Insumos!$A:$J,10,FALSE),IFERROR(VLOOKUP(C5,Preparos!$A:$F,6,FALSE),0))) | H5: =IF(OR(D5="",G5="",F5=0),"",D5*G5*(100/F5))
A6: Ragu | B6: =IF(C6="","",IF(ISNUMBER(MATCH(C6,Insumos!$A:$A,0)),"insumo",IF(ISNUMBER(MATCH(C6,Preparos!$A:$A,0)),"preparo",""))) | C6: Molho de Tomate Base | D6: 1500 | E6: =IF(C6="","",IFERROR(VLOOKUP(C6,Insumos!$A:$I,9,FALSE),IFERROR(VLOOKUP(C6,Preparos!$A:$D,4,FALSE),""))) | F6: =IF(C6="","",IFERROR(VLOOKUP(C6,Insumos!$A:$G,7,FALSE),100)) | G6: =IF(C6="","",IFERROR(VLOOKUP(C6,Insumos!$A:$J,10,FALSE),IFERROR(VLOOKUP(C6,Preparos!$A:$F,6,FALSE),0))) | H6: =IF(OR(D6="",G6="",F6=0),"",D6*G6*(100/F6))
A7: Ragu | B7: =IF(C7="","",IF(ISNUMBER(MATCH(C7,Insumos!$A:$A,0)),"insumo",IF(ISNUMBER(MATCH(C7,Preparos!$A:$A,0)),"preparo",""))) | C7: Carne Moída 80/20 | D7: 1000 | E7: =IF(C7="","",IFERROR(VLOOKUP(C7,Insumos!$A:$I,9,FALSE),IFERROR(VLOOKUP(C7,Preparos!$A:$D,4,FALSE),""))) | F7: =IF(C7="","",IFERROR(VLOOKUP(C7,Insumos!$A:$G,7,FALSE),100)) | G7: =IF(C7="","",IFERROR(VLOOKUP(C7,Insumos!$A:$J,10,FALSE),IFERROR(VLOOKUP(C7,Preparos!$A:$F,6,FALSE),0))) | H7: =IF(OR(D7="",G7="",F7=0),"",D7*G7*(100/F7))
A8: Ragu | B8: =IF(C8="","",IF(ISNUMBER(MATCH(C8,Insumos!$A:$A,0)),"insumo",IF(ISNUMBER(MATCH(C8,Preparos!$A:$A,0)),"preparo",""))) | C8: Cebola | D8: 200 | E8: =IF(C8="","",IFERROR(VLOOKUP(C8,Insumos!$A:$I,9,FALSE),IFERROR(VLOOKUP(C8,Preparos!$A:$D,4,FALSE),""))) | F8: =IF(C8="","",IFERROR(VLOOKUP(C8,Insumos!$A:$G,7,FALSE),100)) | G8: =IF(C8="","",IFERROR(VLOOKUP(C8,Insumos!$A:$J,10,FALSE),IFERROR(VLOOKUP(C8,Preparos!$A:$F,6,FALSE),0))) | H8: =IF(OR(D8="",G8="",F8=0),"",D8*G8*(100/F8))
A9: Hambúrguer Moldado 80g | B9: =IF(C9="","",IF(ISNUMBER(MATCH(C9,Insumos!$A:$A,0)),"insumo",IF(ISNUMBER(MATCH(C9,Preparos!$A:$A,0)),"preparo",""))) | C9: Carne Moída 80/20 | D9: 80 | E9: =IF(C9="","",IFERROR(VLOOKUP(C9,Insumos!$A:$I,9,FALSE),IFERROR(VLOOKUP(C9,Preparos!$A:$D,4,FALSE),""))) | F9: =IF(C9="","",IFERROR(VLOOKUP(C9,Insumos!$A:$G,7,FALSE),100)) | G9: =IF(C9="","",IFERROR(VLOOKUP(C9,Insumos!$A:$J,10,FALSE),IFERROR(VLOOKUP(C9,Preparos!$A:$F,6,FALSE),0))) | H9: =IF(OR(D9="",G9="",F9=0),"",D9*G9*(100/F9))
A10: Massa de Lasanha | B10: =IF(C10="","",IF(ISNUMBER(MATCH(C10,Insumos!$A:$A,0)),"insumo",IF(ISNUMBER(MATCH(C10,Preparos!$A:$A,0)),"preparo",""))) | C10: Farinha Tipo 00 | D10: 700 | E10: =IF(C10="","",IFERROR(VLOOKUP(C10,Insumos!$A:$I,9,FALSE),IFERROR(VLOOKUP(C10,Preparos!$A:$D,4,FALSE),""))) | F10: =IF(C10="","",IFERROR(VLOOKUP(C10,Insumos!$A:$G,7,FALSE),100)) | G10: =IF(C10="","",IFERROR(VLOOKUP(C10,Insumos!$A:$J,10,FALSE),IFERROR(VLOOKUP(C10,Preparos!$A:$F,6,FALSE),0))) | H10: =IF(OR(D10="",G10="",F10=0),"",D10*G10*(100/F10))
A11: Massa de Lasanha | B11: =IF(C11="","",IF(ISNUMBER(MATCH(C11,Insumos!$A:$A,0)),"insumo",IF(ISNUMBER(MATCH(C11,Preparos!$A:$A,0)),"preparo",""))) | C11: Ovo | D11: 7 | E11: =IF(C11="","",IFERROR(VLOOKUP(C11,Insumos!$A:$I,9,FALSE),IFERROR(VLOOKUP(C11,Preparos!$A:$D,4,FALSE),""))) | F11: =IF(C11="","",IFERROR(VLOOKUP(C11,Insumos!$A:$G,7,FALSE),100)) | G11: =IF(C11="","",IFERROR(VLOOKUP(C11,Insumos!$A:$J,10,FALSE),IFERROR(VLOOKUP(C11,Preparos!$A:$F,6,FALSE),0))) | H11: =IF(OR(D11="",G11="",F11=0),"",D11*G11*(100/F11))
B12: =IF(C12="","",IF(ISNUMBER(MATCH(C12,Insumos!$A:$A,0)),"insumo",IF(ISNUMBER(MATCH(C12,Preparos!$A:$A,0)),"preparo",""))) | E12: =IF(C12="","",IFERROR(VLOOKUP(C12,Insumos!$A:$I,9,FALSE),IFERROR(VLOOKUP(C12,Preparos!$A:$D,4,FALSE),""))) | F12: =IF(C12="","",IFERROR(VLOOKUP(C12,Insumos!$A:$G,7,FALSE),100)) | G12: =IF(C12="","",IFERROR(VLOOKUP(C12,Insumos!$A:$J,10,FALSE),IFERROR(VLOOKUP(C12,Preparos!$A:$F,6,FALSE),0))) | H12: =IF(OR(D12="",G12="",F12=0),"",D12*G12*(100/F12))
B13: =IF(C13="","",IF(ISNUMBER(MATCH(C13,Insumos!$A:$A,0)),"insumo",IF(ISNUMBER(MATCH(C13,Preparos!$A:$A,0)),"preparo",""))) | E13: =IF(C13="","",IFERROR(VLOOKUP(C13,Insumos!$A:$I,9,FALSE),IFERROR(VLOOKUP(C13,Preparos!$A:$D,4,FALSE),""))) | F13: =IF(C13="","",IFERROR(VLOOKUP(C13,Insumos!$A:$G,7,FALSE),100)) | G13: =IF(C13="","",IFERROR(VLOOKUP(C13,Insumos!$A:$J,10,FALSE),IFERROR(VLOOKUP(C13,Preparos!$A:$F,6,FALSE),0))) | H13: =IF(OR(D13="",G13="",F13=0),"",D13*G13*(100/F13))
B14: =IF(C14="","",IF(ISNUMBER(MATCH(C14,Insumos!$A:$A,0)),"insumo",IF(ISNUMBER(MATCH(C14,Preparos!$A:$A,0)),"preparo",""))) | E14: =IF(C14="","",IFERROR(VLOOKUP(C14,Insumos!$A:$I,9,FALSE),IFERROR(VLOOKUP(C14,Preparos!$A:$D,4,FALSE),""))) | F14: =IF(C14="","",IFERROR(VLOOKUP(C14,Insumos!$A:$G,7,FALSE),100)) | G14: =IF(C14="","",IFERROR(VLOOKUP(C14,Insumos!$A:$J,10,FALSE),IFERROR(VLOOKUP(C14,Preparos!$A:$F,6,FALSE),0))) | H14: =IF(OR(D14="",G14="",F14=0),"",D14*G14*(100/F14))
B15: =IF(C15="","",IF(ISNUMBER(MATCH(C15,Insumos!$A:$A,0)),"insumo",IF(ISNUMBER(MATCH(C15,Preparos!$A:$A,0)),"preparo",""))) | E15: =IF(C15="","",IFERROR(VLOOKUP(C15,Insumos!$A:$I,9,FALSE),IFERROR(VLOOKUP(C15,Preparos!$A:$D,4,FALSE),""))) | F15: =IF(C15="","",IFERROR(VLOOKUP(C15,Insumos!$A:$G,7,FALSE),100)) | G15: =IF(C15="","",IFERROR(VLOOKUP(C15,Insumos!$A:$J,10,FALSE),IFERROR(VLOOKUP(C15,Preparos!$A:$F,6,FALSE),0))) | H15: =IF(OR(D15="",G15="",F15=0),"",D15*G15*(100/F15))
B16: =IF(C16="","",IF(ISNUMBER(MATCH(C16,Insumos!$A:$A,0)),"insumo",IF(ISNUMBER(MATCH(C16,Preparos!$A:$A,0)),"preparo",""))) | E16: =IF(C16="","",IFERROR(VLOOKUP(C16,Insumos!$A:$I,9,FALSE),IFERROR(VLOOKUP(C16,Preparos!$A:$D,4,FALSE),""))) | F16: =IF(C16="","",IFERROR(VLOOKUP(C16,Insumos!$A:$G,7,FALSE),100)) | G16: =IF(C16="","",IFERROR(VLOOKUP(C16,Insumos!$A:$J,10,FALSE),IFERROR(VLOOKUP(C16,Preparos!$A:$F,6,FALSE),0))) | H16: =IF(OR(D16="",G16="",F16=0),"",D16*G16*(100/F16))
B17: =IF(C17="","",IF(ISNUMBER(MATCH(C17,Insumos!$A:$A,0)),"insumo",IF(ISNUMBER(MATCH(C17,Preparos!$A:$A,0)),"preparo",""))) | E17: =IF(C17="","",IFERROR(VLOOKUP(C17,Insumos!$A:$I,9,FALSE),IFERROR(VLOOKUP(C17,Preparos!$A:$D,4,FALSE),""))) | F17: =IF(C17="","",IFERROR(VLOOKUP(C17,Insumos!$A:$G,7,FALSE),100)) | G17: =IF(C17="","",IFERROR(VLOOKUP(C17,Insumos!$A:$J,10,FALSE),IFERROR(VLOOKUP(C17,Preparos!$A:$F,6,FALSE),0))) | H17: =IF(OR(D17="",G17="",F17=0),"",D17*G17*(100/F17))
B18: =IF(C18="","",IF(ISNUMBER(MATCH(C18,Insumos!$A:$A,0)),"insumo",IF(ISNUMBER(MATCH(C18,Preparos!$A:$A,0)),"preparo",""))) | E18: =IF(C18="","",IFERROR(VLOOKUP(C18,Insumos!$A:$I,9,FALSE),IFERROR(VLOOKUP(C18,Preparos!$A:$D,4,FALSE),""))) | F18: =IF(C18="","",IFERROR(VLOOKUP(C18,Insumos!$A:$G,7,FALSE),100)) | G18: =IF(C18="","",IFERROR(VLOOKUP(C18,Insumos!$A:$J,10,FALSE),IFERROR(VLOOKUP(C18,Preparos!$A:$F,6,FALSE),0))) | H18: =IF(OR(D18="",G18="",F18=0),"",D18*G18*(100/F18))
B19: =IF(C19="","",IF(ISNUMBER(MATCH(C19,Insumos!$A:$A,0)),"insumo",IF(ISNUMBER(MATCH(C19,Preparos!$A:$A,0)),"preparo",""))) | E19: =IF(C19="","",IFERROR(VLOOKUP(C19,Insumos!$A:$I,9,FALSE),IFERROR(VLOOKUP(C19,Preparos!$A:$D,4,FALSE),""))) | F19: =IF(C19="","",IFERROR(VLOOKUP(C19,Insumos!$A:$G,7,FALSE),100)) | G19: =IF(C19="","",IFERROR(VLOOKUP(C19,Insumos!$A:$J,10,FALSE),IFERROR(VLOOKUP(C19,Preparos!$A:$F,6,FALSE),0))) | H19: =IF(OR(D19="",G19="",F19=0),"",D19*G19*(100/F19))
B20: =IF(C20="","",IF(ISNUMBER(MATCH(C20,Insumos!$A:$A,0)),"insumo",IF(ISNUMBER(MATCH(C20,Preparos!$A:$A,0)),"preparo",""))) | E20: =IF(C20="","",IFERROR(VLOOKUP(C20,Insumos!$A:$I,9,FALSE),IFERROR(VLOOKUP(C20,Preparos!$A:$D,4,FALSE),""))) | F20: =IF(C20="","",IFERROR(VLOOKUP(C20,Insumos!$A:$G,7,FALSE),100)) | G20: =IF(C20="","",IFERROR(VLOOKUP(C20,Insumos!$A:$J,10,FALSE),IFERROR(VLOOKUP(C20,Preparos!$A:$F,6,FALSE),0))) | H20: =IF(OR(D20="",G20="",F20=0),"",D20*G20*(100/F20))
B21: =IF(C21="","",IF(ISNUMBER(MATCH(C21,Insumos!$A:$A,0)),"insumo",IF(ISNUMBER(MATCH(C21,Preparos!$A:$A,0)),"preparo",""))) | E21: =IF(C21="","",IFERROR(VLOOKUP(C21,Insumos!$A:$I,9,FALSE),IFERROR(VLOOKUP(C21,Preparos!$A:$D,4,FALSE),""))) | F21: =IF(C21="","",IFERROR(VLOOKUP(C21,Insumos!$A:$G,7,FALSE),100)) | G21: =IF(C21="","",IFERROR(VLOOKUP(C21,Insumos!$A:$J,10,FALSE),IFERROR(VLOOKUP(C21,Preparos!$A:$F,6,FALSE),0))) | H21: =IF(OR(D21="",G21="",F21=0),"",D21*G21*(100/F21))
B22: =IF(C22="","",IF(ISNUMBER(MATCH(C22,Insumos!$A:$A,0)),"insumo",IF(ISNUMBER(MATCH(C22,Preparos!$A:$A,0)),"preparo",""))) | E22: =IF(C22="","",IFERROR(VLOOKUP(C22,Insumos!$A:$I,9,FALSE),IFERROR(VLOOKUP(C22,Preparos!$A:$D,4,FALSE),""))) | F22: =IF(C22="","",IFERROR(VLOOKUP(C22,Insumos!$A:$G,7,FALSE),100)) | G22: =IF(C22="","",IFERROR(VLOOKUP(C22,Insumos!$A:$J,10,FALSE),IFERROR(VLOOKUP(C22,Preparos!$A:$F,6,FALSE),0))) | H22: =IF(OR(D22="",G22="",F22=0),"",D22*G22*(100/F22))
B23: =IF(C23="","",IF(ISNUMBER(MATCH(C23,Insumos!$A:$A,0)),"insumo",IF(ISNUMBER(MATCH(C23,Preparos!$A:$A,0)),"preparo",""))) | E23: =IF(C23="","",IFERROR(VLOOKUP(C23,Insumos!$A:$I,9,FALSE),IFERROR(VLOOKUP(C23,Preparos!$A:$D,4,FALSE),""))) | F23: =IF(C23="","",IFERROR(VLOOKUP(C23,Insumos!$A:$G,7,FALSE),100)) | G23: =IF(C23="","",IFERROR(VLOOKUP(C23,Insumos!$A:$J,10,FALSE),IFERROR(VLOOKUP(C23,Preparos!$A:$F,6,FALSE),0))) | H23: =IF(OR(D23="",G23="",F23=0),"",D23*G23*(100/F23))
... B500: =IF(C500="","",IF(ISNUMBER(MATCH(C500,Insumos!$A:$A,0)),"insumo",IF(ISNUMBER(MATCH(C500,Preparos!$A:$A,0)),"preparo",""))) | E500: =IF(C500="","",IFERROR(VLOOKUP(C500,Insumos!$A:$I,9,FALSE),IFERROR(VLOOKUP(C500,Preparos!$A:$D,4,FALSE),""))) | F500: =IF(C500="","",IFERROR(VLOOKUP(C500,Insumos!$A:$G,7,FALSE),100)) | G500: =IF(C500="","",IFERROR(VLOOKUP(C500,Insumos!$A:$J,10,FALSE),IFERROR(VLOOKUP(C500,Preparos!$A:$F,6,FALSE),0))) | H500: =IF(OR(D500="",G500="",F500=0),"",D500*G500*(100/F500))

Sheet Composicao_Fichas
A1: Ficha | B1: Componente (auto) | C1: Item | D1: Quantidade | E1: Unidade (auto) | F1: Aprov% (auto) | G1: Custo/un (auto) | H1: Custo Linha (auto) | I1: Notas
A2: X-Burger Duplo | B2: =IF(C2="","",IF(ISNUMBER(MATCH(C2,Insumos!$A:$A,0)),"insumo",IF(ISNUMBER(MATCH(C2,Preparos!$A:$A,0)),"preparo",IF(ISNUMBER(MATCH(C2,Fichas!$A:$A,0)),"ficha","")))) | C2: Hambúrguer Moldado 80g | D2: 2 | E2: =IF(C2="","",IFERROR(VLOOKUP(C2,Insumos!$A:$I,9,FALSE),IFERROR(VLOOKUP(C2,Preparos!$A:$D,4,FALSE),IFERROR(IF(ISNUMBER(MATCH(C2,Fichas!$A:$A,0)),"un",""),"")))) | F2: =IF(C2="","",IFERROR(VLOOKUP(C2,Insumos!$A:$G,7,FALSE),100)) | G2: =IF(C2="","",IFERROR(VLOOKUP(C2,Insumos!$A:$J,10,FALSE),IFERROR(VLOOKUP(C2,Preparos!$A:$F,6,FALSE),IFERROR(VLOOKUP(C2,Fichas!$A:$D,4,FALSE),0)))) | H2: =IF(OR(D2="",G2="",F2=0),"",D2*G2*(100/F2))
A3: X-Burger Duplo | B3: =IF(C3="","",IF(ISNUMBER(MATCH(C3,Insumos!$A:$A,0)),"insumo",IF(ISNUMBER(MATCH(C3,Preparos!$A:$A,0)),"preparo",IF(ISNUMBER(MATCH(C3,Fichas!$A:$A,0)),"ficha","")))) | C3: Pão de Hambúrguer | D3: 1 | E3: =IF(C3="","",IFERROR(VLOOKUP(C3,Insumos!$A:$I,9,FALSE),IFERROR(VLOOKUP(C3,Preparos!$A:$D,4,FALSE),IFERROR(IF(ISNUMBER(MATCH(C3,Fichas!$A:$A,0)),"un",""),"")))) | F3: =IF(C3="","",IFERROR(VLOOKUP(C3,Insumos!$A:$G,7,FALSE),100)) | G3: =IF(C3="","",IFERROR(VLOOKUP(C3,Insumos!$A:$J,10,FALSE),IFERROR(VLOOKUP(C3,Preparos!$A:$F,6,FALSE),IFERROR(VLOOKUP(C3,Fichas!$A:$D,4,FALSE),0)))) | H3: =IF(OR(D3="",G3="",F3=0),"",D3*G3*(100/F3))
A4: X-Burger Duplo | B4: =IF(C4="","",IF(ISNUMBER(MATCH(C4,Insumos!$A:$A,0)),"insumo",IF(ISNUMBER(MATCH(C4,Preparos!$A:$A,0)),"preparo",IF(ISNUMBER(MATCH(C4,Fichas!$A:$A,0)),"ficha","")))) | C4: Queijo Muçarela | D4: 50 | E4: =IF(C4="","",IFERROR(VLOOKUP(C4,Insumos!$A:$I,9,FALSE),IFERROR(VLOOKUP(C4,Preparos!$A:$D,4,FALSE),IFERROR(IF(ISNUMBER(MATCH(C4,Fichas!$A:$A,0)),"un",""),"")))) | F4: =IF(C4="","",IFERROR(VLOOKUP(C4,Insumos!$A:$G,7,FALSE),100)) | G4: =IF(C4="","",IFERROR(VLOOKUP(C4,Insumos!$A:$J,10,FALSE),IFERROR(VLOOKUP(C4,Preparos!$A:$F,6,FALSE),IFERROR(VLOOKUP(C4,Fichas!$A:$D,4,FALSE),0)))) | H4: =IF(OR(D4="",G4="",F4=0),"",D4*G4*(100/F4))
A5: X-Burger Duplo | B5: =IF(C5="","",IF(ISNUMBER(MATCH(C5,Insumos!$A:$A,0)),"insumo",IF(ISNUMBER(MATCH(C5,Preparos!$A:$A,0)),"preparo",IF(ISNUMBER(MATCH(C5,Fichas!$A:$A,0)),"ficha","")))) | C5: Caixa Delivery | D5: 1 | E5: =IF(C5="","",IFERROR(VLOOKUP(C5,Insumos!$A:$I,9,FALSE),IFERROR(VLOOKUP(C5,Preparos!$A:$D,4,FALSE),IFERROR(IF(ISNUMBER(MATCH(C5,Fichas!$A:$A,0)),"un",""),"")))) | F5: =IF(C5="","",IFERROR(VLOOKUP(C5,Insumos!$A:$G,7,FALSE),100)) | G5: =IF(C5="","",IFERROR(VLOOKUP(C5,Insumos!$A:$J,10,FALSE),IFERROR(VLOOKUP(C5,Preparos!$A:$F,6,FALSE),IFERROR(VLOOKUP(C5,Fichas!$A:$D,4,FALSE),0)))) | H5: =IF(OR(D5="",G5="",F5=0),"",D5*G5*(100/F5))
A6: Lasanha à Bolonhesa | B6: =IF(C6="","",IF(ISNUMBER(MATCH(C6,Insumos!$A:$A,0)),"insumo",IF(ISNUMBER(MATCH(C6,Preparos!$A:$A,0)),"preparo",IF(ISNUMBER(MATCH(C6,Fichas!$A:$A,0)),"ficha","")))) | C6: Ragu | D6: 400 | E6: =IF(C6="","",IFERROR(VLOOKUP(C6,Insumos!$A:$I,9,FALSE),IFERROR(VLOOKUP(C6,Preparos!$A:$D,4,FALSE),IFERROR(IF(ISNUMBER(MATCH(C6,Fichas!$A:$A,0)),"un",""),"")))) | F6: =IF(C6="","",IFERROR(VLOOKUP(C6,Insumos!$A:$G,7,FALSE),100)) | G6: =IF(C6="","",IFERROR(VLOOKUP(C6,Insumos!$A:$J,10,FALSE),IFERROR(VLOOKUP(C6,Preparos!$A:$F,6,FALSE),IFERROR(VLOOKUP(C6,Fichas!$A:$D,4,FALSE),0)))) | H6: =IF(OR(D6="",G6="",F6=0),"",D6*G6*(100/F6))
A7: Lasanha à Bolonhesa | B7: =IF(C7="","",IF(ISNUMBER(MATCH(C7,Insumos!$A:$A,0)),"insumo",IF(ISNUMBER(MATCH(C7,Preparos!$A:$A,0)),"preparo",IF(ISNUMBER(MATCH(C7,Fichas!$A:$A,0)),"ficha","")))) | C7: Massa de Lasanha | D7: 200 | E7: =IF(C7="","",IFERROR(VLOOKUP(C7,Insumos!$A:$I,9,FALSE),IFERROR(VLOOKUP(C7,Preparos!$A:$D,4,FALSE),IFERROR(IF(ISNUMBER(MATCH(C7,Fichas!$A:$A,0)),"un",""),"")))) | F7: =IF(C7="","",IFERROR(VLOOKUP(C7,Insumos!$A:$G,7,FALSE),100)) | G7: =IF(C7="","",IFERROR(VLOOKUP(C7,Insumos!$A:$J,10,FALSE),IFERROR(VLOOKUP(C7,Preparos!$A:$F,6,FALSE),IFERROR(VLOOKUP(C7,Fichas!$A:$D,4,FALSE),0)))) | H7: =IF(OR(D7="",G7="",F7=0),"",D7*G7*(100/F7))
A8: Lasanha à Bolonhesa | B8: =IF(C8="","",IF(ISNUMBER(MATCH(C8,Insumos!$A:$A,0)),"insumo",IF(ISNUMBER(MATCH(C8,Preparos!$A:$A,0)),"preparo",IF(ISNUMBER(MATCH(C8,Fichas!$A:$A,0)),"ficha","")))) | C8: Queijo Muçarela | D8: 150 | E8: =IF(C8="","",IFERROR(VLOOKUP(C8,Insumos!$A:$I,9,FALSE),IFERROR(VLOOKUP(C8,Preparos!$A:$D,4,FALSE),IFERROR(IF(ISNUMBER(MATCH(C8,Fichas!$A:$A,0)),"un",""),"")))) | F8: =IF(C8="","",IFERROR(VLOOKUP(C8,Insumos!$A:$G,7,FALSE),100)) | G8: =IF(C8="","",IFERROR(VLOOKUP(C8,Insumos!$A:$J,10,FALSE),IFERROR(VLOOKUP(C8,Preparos!$A:$F,6,FALSE),IFERROR(VLOOKUP(C8,Fichas!$A:$D,4,FALSE),0)))) | H8: =IF(OR(D8="",G8="",F8=0),"",D8*G8*(100/F8))
A9: Lasanha à Bolonhesa | B9: =IF(C9="","",IF(ISNUMBER(MATCH(C9,Insumos!$A:$A,0)),"insumo",IF(ISNUMBER(MATCH(C9,Preparos!$A:$A,0)),"preparo",IF(ISNUMBER(MATCH(C9,Fichas!$A:$A,0)),"ficha","")))) | C9: Queijo Parmesão | D9: 30 | E9: =IF(C9="","",IFERROR(VLOOKUP(C9,Insumos!$A:$I,9,FALSE),IFERROR(VLOOKUP(C9,Preparos!$A:$D,4,FALSE),IFERROR(IF(ISNUMBER(MATCH(C9,Fichas!$A:$A,0)),"un",""),"")))) | F9: =IF(C9="","",IFERROR(VLOOKUP(C9,Insumos!$A:$G,7,FALSE),100)) | G9: =IF(C9="","",IFERROR(VLOOKUP(C9,Insumos!$A:$J,10,FALSE),IFERROR(VLOOKUP(C9,Preparos!$A:$F,6,FALSE),IFERROR(VLOOKUP(C9,Fichas!$A:$D,4,FALSE),0)))) | H9: =IF(OR(D9="",G9="",F9=0),"",D9*G9*(100/F9))
A10: Salmão Grelhado | B10: =IF(C10="","",IF(ISNUMBER(MATCH(C10,Insumos!$A:$A,0)),"insumo",IF(ISNUMBER(MATCH(C10,Preparos!$A:$A,0)),"preparo",IF(ISNUMBER(MATCH(C10,Fichas!$A:$A,0)),"ficha","")))) | C10: Salmão Fresco | D10: 200 | E10: =IF(C10="","",IFERROR(VLOOKUP(C10,Insumos!$A:$I,9,FALSE),IFERROR(VLOOKUP(C10,Preparos!$A:$D,4,FALSE),IFERROR(IF(ISNUMBER(MATCH(C10,Fichas!$A:$A,0)),"un",""),"")))) | F10: =IF(C10="","",IFERROR(VLOOKUP(C10,Insumos!$A:$G,7,FALSE),100)) | G10: =IF(C10="","",IFERROR(VLOOKUP(C10,Insumos!$A:$J,10,FALSE),IFERROR(VLOOKUP(C10,Preparos!$A:$F,6,FALSE),IFERROR(VLOOKUP(C10,Fichas!$A:$D,4,FALSE),0)))) | H10: =IF(OR(D10="",G10="",F10=0),"",D10*G10*(100/F10))
A11: Salmão Grelhado | B11: =IF(C11="","",IF(ISNUMBER(MATCH(C11,Insumos!$A:$A,0)),"insumo",IF(ISNUMBER(MATCH(C11,Preparos!$A:$A,0)),"preparo",IF(ISNUMBER(MATCH(C11,Fichas!$A:$A,0)),"ficha","")))) | C11: Azeite Extra Virgem | D11: 20 | E11: =IF(C11="","",IFERROR(VLOOKUP(C11,Insumos!$A:$I,9,FALSE),IFERROR(VLOOKUP(C11,Preparos!$A:$D,4,FALSE),IFERROR(IF(ISNUMBER(MATCH(C11,Fichas!$A:$A,0)),"un",""),"")))) | F11: =IF(C11="","",IFERROR(VLOOKUP(C11,Insumos!$A:$G,7,FALSE),100)) | G11: =IF(C11="","",IFERROR(VLOOKUP(C11,Insumos!$A:$J,10,FALSE),IFERROR(VLOOKUP(C11,Preparos!$A:$F,6,FALSE),IFERROR(VLOOKUP(C11,Fichas!$A:$D,4,FALSE),0)))) | H11: =IF(OR(D11="",G11="",F11=0),"",D11*G11*(100/F11))
B12: =IF(C12="","",IF(ISNUMBER(MATCH(C12,Insumos!$A:$A,0)),"insumo",IF(ISNUMBER(MATCH(C12,Preparos!$A:$A,0)),"preparo",IF(ISNUMBER(MATCH(C12,Fichas!$A:$A,0)),"ficha","")))) | E12: =IF(C12="","",IFERROR(VLOOKUP(C12,Insumos!$A:$I,9,FALSE),IFERROR(VLOOKUP(C12,Preparos!$A:$D,4,FALSE),IFERROR(IF(ISNUMBER(MATCH(C12,Fichas!$A:$A,0)),"un",""),"")))) | F12: =IF(C12="","",IFERROR(VLOOKUP(C12,Insumos!$A:$G,7,FALSE),100)) | G12: =IF(C12="","",IFERROR(VLOOKUP(C12,Insumos!$A:$J,10,FALSE),IFERROR(VLOOKUP(C12,Preparos!$A:$F,6,FALSE),IFERROR(VLOOKUP(C12,Fichas!$A:$D,4,FALSE),0)))) | H12: =IF(OR(D12="",G12="",F12=0),"",D12*G12*(100/F12))
B13: =IF(C13="","",IF(ISNUMBER(MATCH(C13,Insumos!$A:$A,0)),"insumo",IF(ISNUMBER(MATCH(C13,Preparos!$A:$A,0)),"preparo",IF(ISNUMBER(MATCH(C13,Fichas!$A:$A,0)),"ficha","")))) | E13: =IF(C13="","",IFERROR(VLOOKUP(C13,Insumos!$A:$I,9,FALSE),IFERROR(VLOOKUP(C13,Preparos!$A:$D,4,FALSE),IFERROR(IF(ISNUMBER(MATCH(C13,Fichas!$A:$A,0)),"un",""),"")))) | F13: =IF(C13="","",IFERROR(VLOOKUP(C13,Insumos!$A:$G,7,FALSE),100)) | G13: =IF(C13="","",IFERROR(VLOOKUP(C13,Insumos!$A:$J,10,FALSE),IFERROR(VLOOKUP(C13,Preparos!$A:$F,6,FALSE),IFERROR(VLOOKUP(C13,Fichas!$A:$D,4,FALSE),0)))) | H13: =IF(OR(D13="",G13="",F13=0),"",D13*G13*(100/F13))
B14: =IF(C14="","",IF(ISNUMBER(MATCH(C14,Insumos!$A:$A,0)),"insumo",IF(ISNUMBER(MATCH(C14,Preparos!$A:$A,0)),"preparo",IF(ISNUMBER(MATCH(C14,Fichas!$A:$A,0)),"ficha","")))) | E14: =IF(C14="","",IFERROR(VLOOKUP(C14,Insumos!$A:$I,9,FALSE),IFERROR(VLOOKUP(C14,Preparos!$A:$D,4,FALSE),IFERROR(IF(ISNUMBER(MATCH(C14,Fichas!$A:$A,0)),"un",""),"")))) | F14: =IF(C14="","",IFERROR(VLOOKUP(C14,Insumos!$A:$G,7,FALSE),100)) | G14: =IF(C14="","",IFERROR(VLOOKUP(C14,Insumos!$A:$J,10,FALSE),IFERROR(VLOOKUP(C14,Preparos!$A:$F,6,FALSE),IFERROR(VLOOKUP(C14,Fichas!$A:$D,4,FALSE),0)))) | H14: =IF(OR(D14="",G14="",F14=0),"",D14*G14*(100/F14))
B15: =IF(C15="","",IF(ISNUMBER(MATCH(C15,Insumos!$A:$A,0)),"insumo",IF(ISNUMBER(MATCH(C15,Preparos!$A:$A,0)),"preparo",IF(ISNUMBER(MATCH(C15,Fichas!$A:$A,0)),"ficha","")))) | E15: =IF(C15="","",IFERROR(VLOOKUP(C15,Insumos!$A:$I,9,FALSE),IFERROR(VLOOKUP(C15,Preparos!$A:$D,4,FALSE),IFERROR(IF(ISNUMBER(MATCH(C15,Fichas!$A:$A,0)),"un",""),"")))) | F15: =IF(C15="","",IFERROR(VLOOKUP(C15,Insumos!$A:$G,7,FALSE),100)) | G15: =IF(C15="","",IFERROR(VLOOKUP(C15,Insumos!$A:$J,10,FALSE),IFERROR(VLOOKUP(C15,Preparos!$A:$F,6,FALSE),IFERROR(VLOOKUP(C15,Fichas!$A:$D,4,FALSE),0)))) | H15: =IF(OR(D15="",G15="",F15=0),"",D15*G15*(100/F15))
B16: =IF(C16="","",IF(ISNUMBER(MATCH(C16,Insumos!$A:$A,0)),"insumo",IF(ISNUMBER(MATCH(C16,Preparos!$A:$A,0)),"preparo",IF(ISNUMBER(MATCH(C16,Fichas!$A:$A,0)),"ficha","")))) | E16: =IF(C16="","",IFERROR(VLOOKUP(C16,Insumos!$A:$I,9,FALSE),IFERROR(VLOOKUP(C16,Preparos!$A:$D,4,FALSE),IFERROR(IF(ISNUMBER(MATCH(C16,Fichas!$A:$A,0)),"un",""),"")))) | F16: =IF(C16="","",IFERROR(VLOOKUP(C16,Insumos!$A:$G,7,FALSE),100)) | G16: =IF(C16="","",IFERROR(VLOOKUP(C16,Insumos!$A:$J,10,FALSE),IFERROR(VLOOKUP(C16,Preparos!$A:$F,6,FALSE),IFERROR(VLOOKUP(C16,Fichas!$A:$D,4,FALSE),0)))) | H16: =IF(OR(D16="",G16="",F16=0),"",D16*G16*(100/F16))
B17: =IF(C17="","",IF(ISNUMBER(MATCH(C17,Insumos!$A:$A,0)),"insumo",IF(ISNUMBER(MATCH(C17,Preparos!$A:$A,0)),"preparo",IF(ISNUMBER(MATCH(C17,Fichas!$A:$A,0)),"ficha","")))) | E17: =IF(C17="","",IFERROR(VLOOKUP(C17,Insumos!$A:$I,9,FALSE),IFERROR(VLOOKUP(C17,Preparos!$A:$D,4,FALSE),IFERROR(IF(ISNUMBER(MATCH(C17,Fichas!$A:$A,0)),"un",""),"")))) | F17: =IF(C17="","",IFERROR(VLOOKUP(C17,Insumos!$A:$G,7,FALSE),100)) | G17: =IF(C17="","",IFERROR(VLOOKUP(C17,Insumos!$A:$J,10,FALSE),IFERROR(VLOOKUP(C17,Preparos!$A:$F,6,FALSE),IFERROR(VLOOKUP(C17,Fichas!$A:$D,4,FALSE),0)))) | H17: =IF(OR(D17="",G17="",F17=0),"",D17*G17*(100/F17))
B18: =IF(C18="","",IF(ISNUMBER(MATCH(C18,Insumos!$A:$A,0)),"insumo",IF(ISNUMBER(MATCH(C18,Preparos!$A:$A,0)),"preparo",IF(ISNUMBER(MATCH(C18,Fichas!$A:$A,0)),"ficha","")))) | E18: =IF(C18="","",IFERROR(VLOOKUP(C18,Insumos!$A:$I,9,FALSE),IFERROR(VLOOKUP(C18,Preparos!$A:$D,4,FALSE),IFERROR(IF(ISNUMBER(MATCH(C18,Fichas!$A:$A,0)),"un",""),"")))) | F18: =IF(C18="","",IFERROR(VLOOKUP(C18,Insumos!$A:$G,7,FALSE),100)) | G18: =IF(C18="","",IFERROR(VLOOKUP(C18,Insumos!$A:$J,10,FALSE),IFERROR(VLOOKUP(C18,Preparos!$A:$F,6,FALSE),IFERROR(VLOOKUP(C18,Fichas!$A:$D,4,FALSE),0)))) | H18: =IF(OR(D18="",G18="",F18=0),"",D18*G18*(100/F18))
B19: =IF(C19="","",IF(ISNUMBER(MATCH(C19,Insumos!$A:$A,0)),"insumo",IF(ISNUMBER(MATCH(C19,Preparos!$A:$A,0)),"preparo",IF(ISNUMBER(MATCH(C19,Fichas!$A:$A,0)),"ficha","")))) | E19: =IF(C19="","",IFERROR(VLOOKUP(C19,Insumos!$A:$I,9,FALSE),IFERROR(VLOOKUP(C19,Preparos!$A:$D,4,FALSE),IFERROR(IF(ISNUMBER(MATCH(C19,Fichas!$A:$A,0)),"un",""),"")))) | F19: =IF(C19="","",IFERROR(VLOOKUP(C19,Insumos!$A:$G,7,FALSE),100)) | G19: =IF(C19="","",IFERROR(VLOOKUP(C19,Insumos!$A:$J,10,FALSE),IFERROR(VLOOKUP(C19,Preparos!$A:$F,6,FALSE),IFERROR(VLOOKUP(C19,Fichas!$A:$D,4,FALSE),0)))) | H19: =IF(OR(D19="",G19="",F19=0),"",D19*G19*(100/F19))
B20: =IF(C20="","",IF(ISNUMBER(MATCH(C20,Insumos!$A:$A,0)),"insumo",IF(ISNUMBER(MATCH(C20,Preparos!$A:$A,0)),"preparo",IF(ISNUMBER(MATCH(C20,Fichas!$A:$A,0)),"ficha","")))) | E20: =IF(C20="","",IFERROR(VLOOKUP(C20,Insumos!$A:$I,9,FALSE),IFERROR(VLOOKUP(C20,Preparos!$A:$D,4,FALSE),IFERROR(IF(ISNUMBER(MATCH(C20,Fichas!$A:$A,0)),"un",""),"")))) | F20: =IF(C20="","",IFERROR(VLOOKUP(C20,Insumos!$A:$G,7,FALSE),100)) | G20: =IF(C20="","",IFERROR(VLOOKUP(C20,Insumos!$A:$J,10,FALSE),IFERROR(VLOOKUP(C20,Preparos!$A:$F,6,FALSE),IFERROR(VLOOKUP(C20,Fichas!$A:$D,4,FALSE),0)))) | H20: =IF(OR(D20="",G20="",F20=0),"",D20*G20*(100/F20))
B21: =IF(C21="","",IF(ISNUMBER(MATCH(C21,Insumos!$A:$A,0)),"insumo",IF(ISNUMBER(MATCH(C21,Preparos!$A:$A,0)),"preparo",IF(ISNUMBER(MATCH(C21,Fichas!$A:$A,0)),"ficha","")))) | E21: =IF(C21="","",IFERROR(VLOOKUP(C21,Insumos!$A:$I,9,FALSE),IFERROR(VLOOKUP(C21,Preparos!$A:$D,4,FALSE),IFERROR(IF(ISNUMBER(MATCH(C21,Fichas!$A:$A,0)),"un",""),"")))) | F21: =IF(C21="","",IFERROR(VLOOKUP(C21,Insumos!$A:$G,7,FALSE),100)) | G21: =IF(C21="","",IFERROR(VLOOKUP(C21,Insumos!$A:$J,10,FALSE),IFERROR(VLOOKUP(C21,Preparos!$A:$F,6,FALSE),IFERROR(VLOOKUP(C21,Fichas!$A:$D,4,FALSE),0)))) | H21: =IF(OR(D21="",G21="",F21=0),"",D21*G21*(100/F21))
B22: =IF(C22="","",IF(ISNUMBER(MATCH(C22,Insumos!$A:$A,0)),"insumo",IF(ISNUMBER(MATCH(C22,Preparos!$A:$A,0)),"preparo",IF(ISNUMBER(MATCH(C22,Fichas!$A:$A,0)),"ficha","")))) | E22: =IF(C22="","",IFERROR(VLOOKUP(C22,Insumos!$A:$I,9,FALSE),IFERROR(VLOOKUP(C22,Preparos!$A:$D,4,FALSE),IFERROR(IF(ISNUMBER(MATCH(C22,Fichas!$A:$A,0)),"un",""),"")))) | F22: =IF(C22="","",IFERROR(VLOOKUP(C22,Insumos!$A:$G,7,FALSE),100)) | G22: =IF(C22="","",IFERROR(VLOOKUP(C22,Insumos!$A:$J,10,FALSE),IFERROR(VLOOKUP(C22,Preparos!$A:$F,6,FALSE),IFERROR(VLOOKUP(C22,Fichas!$A:$D,4,FALSE),0)))) | H22: =IF(OR(D22="",G22="",F22=0),"",D22*G22*(100/F22))
B23: =IF(C23="","",IF(ISNUMBER(MATCH(C23,Insumos!$A:$A,0)),"insumo",IF(ISNUMBER(MATCH(C23,Preparos!$A:$A,0)),"preparo",IF(ISNUMBER(MATCH(C23,Fichas!$A:$A,0)),"ficha","")))) | E23: =IF(C23="","",IFERROR(VLOOKUP(C23,Insumos!$A:$I,9,FALSE),IFERROR(VLOOKUP(C23,Preparos!$A:$D,4,FALSE),IFERROR(IF(ISNUMBER(MATCH(C23,Fichas!$A:$A,0)),"un",""),"")))) | F23: =IF(C23="","",IFERROR(VLOOKUP(C23,Insumos!$A:$G,7,FALSE),100)) | G23: =IF(C23="","",IFERROR(VLOOKUP(C23,Insumos!$A:$J,10,FALSE),IFERROR(VLOOKUP(C23,Preparos!$A:$F,6,FALSE),IFERROR(VLOOKUP(C23,Fichas!$A:$D,4,FALSE),0)))) | H23: =IF(OR(D23="",G23="",F23=0),"",D23*G23*(100/F23))
... B500: =IF(C500="","",IF(ISNUMBER(MATCH(C500,Insumos!$A:$A,0)),"insumo",IF(ISNUMBER(MATCH(C500,Preparos!$A:$A,0)),"preparo",IF(ISNUMBER(MATCH(C500,Fichas!$A:$A,0)),"ficha","")))) | E500: =IF(C500="","",IFERROR(VLOOKUP(C500,Insumos!$A:$I,9,FALSE),IFERROR(VLOOKUP(C500,Preparos!$A:$D,4,FALSE),IFERROR(IF(ISNUMBER(MATCH(C500,Fichas!$A:$A,0)),"un",""),"")))) | F500: =IF(C500="","",IFERROR(VLOOKUP(C500,Insumos!$A:$G,7,FALSE),100)) | G500: =IF(C500="","",IFERROR(VLOOKUP(C500,Insumos!$A:$J,10,FALSE),IFERROR(VLOOKUP(C500,Preparos!$A:$F,6,FALSE),IFERROR(VLOOKUP(C500,Fichas!$A:$D,4,FALSE),0)))) | H500: =IF(OR(D500="",G500="",F500=0),"",D500*G500*(100/F500))

Sheet Ver_Ficha
B2: 👁 FICHA TÉCNICA
B4: Escolha: | C4: X-Burger Duplo
B6: Categoria: | C6: =IFERROR(VLOOKUP($C$4,Fichas!$A:$F,2,FALSE),"")
B7: Preço de Venda: | C7: =IFERROR(VLOOKUP($C$4,Fichas!$A:$F,3,FALSE),"")
B8: Custo Total: | C8: =IFERROR(VLOOKUP($C$4,Fichas!$A:$F,4,FALSE),"")
B9: CMV: | C9: =IFERROR(VLOOKUP($C$4,Fichas!$A:$F,5,FALSE),"")
B11: INGREDIENTES | D11: QTD | E11: R$
B12: =IFERROR(INDEX(Composicao_Fichas!$C:$C,SMALL(IF(Composicao_Fichas!$A$2:$A$500=$C$4,ROW(Composicao_Fichas!$A$2:$A$500)),1)),"") | D12: =IF($B12="","",IFERROR(INDEX(Composicao_Fichas!$D:$D,SMALL(IF(Composicao_Fichas!$A$2:$A$500=$C$4,ROW(Composicao_Fichas!$A$2:$A$500)),1))&" "&INDEX(Composicao_Fichas!$E:$E,SMALL(IF(Composicao_Fichas!$A$2:$A$500=$C$4,ROW(Composicao_Fichas!$A$2:$A$500)),1)),"")) | E12: =IFERROR(INDEX(Composicao_Fichas!$H:$H,SMALL(IF(Composicao_Fichas!$A$2:$A$500=$C$4,ROW(Composicao_Fichas!$A$2:$A$500)),1)),"")
B13: =IFERROR(INDEX(Composicao_Fichas!$C:$C,SMALL(IF(Composicao_Fichas!$A$2:$A$500=$C$4,ROW(Composicao_Fichas!$A$2:$A$500)),2)),"") | D13: =IF($B13="","",IFERROR(INDEX(Composicao_Fichas!$D:$D,SMALL(IF(Composicao_Fichas!$A$2:$A$500=$C$4,ROW(Composicao_Fichas!$A$2:$A$500)),2))&" "&INDEX(Composicao_Fichas!$E:$E,SMALL(IF(Composicao_Fichas!$A$2:$A$500=$C$4,ROW(Composicao_Fichas!$A$2:$A$500)),2)),"")) | E13: =IFERROR(INDEX(Composicao_Fichas!$H:$H,SMALL(IF(Composicao_Fichas!$A$2:$A$500=$C$4,ROW(Composicao_Fichas!$A$2:$A$500)),2)),"")
B14: =IFERROR(INDEX(Composicao_Fichas!$C:$C,SMALL(IF(Composicao_Fichas!$A$2:$A$500=$C$4,ROW(Composicao_Fichas!$A$2:$A$500)),3)),"") | D14: =IF($B14="","",IFERROR(INDEX(Composicao_Fichas!$D:$D,SMALL(IF(Composicao_Fichas!$A$2:$A$500=$C$4,ROW(Composicao_Fichas!$A$2:$A$500)),3))&" "&INDEX(Composicao_Fichas!$E:$E,SMALL(IF(Composicao_Fichas!$A$2:$A$500=$C$4,ROW(Composicao_Fichas!$A$2:$A$500)),3)),"")) | E14: =IFERROR(INDEX(Composicao_Fichas!$H:$H,SMALL(IF(Composicao_Fichas!$A$2:$A$500=$C$4,ROW(Composicao_Fichas!$A$2:$A$500)),3)),"")
B15: =IFERROR(INDEX(Composicao_Fichas!$C:$C,SMALL(IF(Composicao_Fichas!$A$2:$A$500=$C$4,ROW(Composicao_Fichas!$A$2:$A$500)),4)),"") | D15: =IF($B15="","",IFERROR(INDEX(Composicao_Fichas!$D:$D,SMALL(IF(Composicao_Fichas!$A$2:$A$500=$C$4,ROW(Composicao_Fichas!$A$2:$A$500)),4))&" "&INDEX(Composicao_Fichas!$E:$E,SMALL(IF(Composicao_Fichas!$A$2:$A$500=$C$4,ROW(Composicao_Fichas!$A$2:$A$500)),4)),"")) | E15: =IFERROR(INDEX(Composicao_Fichas!$H:$H,SMALL(IF(Composicao_Fichas!$A$2:$A$500=$C$4,ROW(Composicao_Fichas!$A$2:$A$500)),4)),"")
B16: =IFERROR(INDEX(Composicao_Fichas!$C:$C,SMALL(IF(Composicao_Fichas!$A$2:$A$500=$C$4,ROW(Composicao_Fichas!$A$2:$A$500)),5)),"") | D16: =IF($B16="","",IFERROR(INDEX(Composicao_Fichas!$D:$D,SMALL(IF(Composicao_Fichas!$A$2:$A$500=$C$4,ROW(Composicao_Fichas!$A$2:$A$500)),5))&" "&INDEX(Composicao_Fichas!$E:$E,SMALL(IF(Composicao_Fichas!$A$2:$A$500=$C$4,ROW(Composicao_Fichas!$A$2:$A$500)),5)),"")) | E16: =IFERROR(INDEX(Composicao_Fichas!$H:$H,SMALL(IF(Composicao_Fichas!$A$2:$A$500=$C$4,ROW(Composicao_Fichas!$A$2:$A$500)),5)),"")
B17: =IFERROR(INDEX(Composicao_Fichas!$C:$C,SMALL(IF(Composicao_Fichas!$A$2:$A$500=$C$4,ROW(Composicao_Fichas!$A$2:$A$500)),6)),"") | D17: =IF($B17="","",IFERROR(INDEX(Composicao_Fichas!$D:$D,SMALL(IF(Composicao_Fichas!$A$2:$A$500=$C$4,ROW(Composicao_Fichas!$A$2:$A$500)),6))&" "&INDEX(Composicao_Fichas!$E:$E,SMALL(IF(Composicao_Fichas!$A$2:$A$500=$C$4,ROW(Composicao_Fichas!$A$2:$A$500)),6)),"")) | E17: =IFERROR(INDEX(Composicao_Fichas!$H:$H,SMALL(IF(Composicao_Fichas!$A$2:$A$500=$C$4,ROW(Composicao_Fichas!$A$2:$A$500)),6)),"")
B18: =IFERROR(INDEX(Composicao_Fichas!$C:$C,SMALL(IF(Composicao_Fichas!$A$2:$A$500=$C$4,ROW(Composicao_Fichas!$A$2:$A$500)),7)),"") | D18: =IF($B18="","",IFERROR(INDEX(Composicao_Fichas!$D:$D,SMALL(IF(Composicao_Fichas!$A$2:$A$500=$C$4,ROW(Composicao_Fichas!$A$2:$A$500)),7))&" "&INDEX(Composicao_Fichas!$E:$E,SMALL(IF(Composicao_Fichas!$A$2:$A$500=$C$4,ROW(Composicao_Fichas!$A$2:$A$500)),7)),"")) | E18: =IFERROR(INDEX(Composicao_Fichas!$H:$H,SMALL(IF(Composicao_Fichas!$A$2:$A$500=$C$4,ROW(Composicao_Fichas!$A$2:$A$500)),7)),"")
B19: =IFERROR(INDEX(Composicao_Fichas!$C:$C,SMALL(IF(Composicao_Fichas!$A$2:$A$500=$C$4,ROW(Composicao_Fichas!$A$2:$A$500)),8)),"") | D19: =IF($B19="","",IFERROR(INDEX(Composicao_Fichas!$D:$D,SMALL(IF(Composicao_Fichas!$A$2:$A$500=$C$4,ROW(Composicao_Fichas!$A$2:$A$500)),8))&" "&INDEX(Composicao_Fichas!$E:$E,SMALL(IF(Composicao_Fichas!$A$2:$A$500=$C$4,ROW(Composicao_Fichas!$A$2:$A$500)),8)),"")) | E19: =IFERROR(INDEX(Composicao_Fichas!$H:$H,SMALL(IF(Composicao_Fichas!$A$2:$A$500=$C$4,ROW(Composicao_Fichas!$A$2:$A$500)),8)),"")
B20: =IFERROR(INDEX(Composicao_Fichas!$C:$C,SMALL(IF(Composicao_Fichas!$A$2:$A$500=$C$4,ROW(Composicao_Fichas!$A$2:$A$500)),9)),"") | D20: =IF($B20="","",IFERROR(INDEX(Composicao_Fichas!$D:$D,SMALL(IF(Composicao_Fichas!$A$2:$A$500=$C$4,ROW(Composicao_Fichas!$A$2:$A$500)),9))&" "&INDEX(Composicao_Fichas!$E:$E,SMALL(IF(Composicao_Fichas!$A$2:$A$500=$C$4,ROW(Composicao_Fichas!$A$2:$A$500)),9)),"")) | E20: =IFERROR(INDEX(Composicao_Fichas!$H:$H,SMALL(IF(Composicao_Fichas!$A$2:$A$500=$C$4,ROW(Composicao_Fichas!$A$2:$A$500)),9)),"")
B21: =IFERROR(INDEX(Composicao_Fichas!$C:$C,SMALL(IF(Composicao_Fichas!$A$2:$A$500=$C$4,ROW(Composicao_Fichas!$A$2:$A$500)),10)),"") | D21: =IF($B21="","",IFERROR(INDEX(Composicao_Fichas!$D:$D,SMALL(IF(Composicao_Fichas!$A$2:$A$500=$C$4,ROW(Composicao_Fichas!$A$2:$A$500)),10))&" "&INDEX(Composicao_Fichas!$E:$E,SMALL(IF(Composicao_Fichas!$A$2:$A$500=$C$4,ROW(Composicao_Fichas!$A$2:$A$500)),10)),"")) | E21: =IFERROR(INDEX(Composicao_Fichas!$H:$H,SMALL(IF(Composicao_Fichas!$A$2:$A$500=$C$4,ROW(Composicao_Fichas!$A$2:$A$500)),10)),"")
B22: =IFERROR(INDEX(Composicao_Fichas!$C:$C,SMALL(IF(Composicao_Fichas!$A$2:$A$500=$C$4,ROW(Composicao_Fichas!$A$2:$A$500)),11)),"") | D22: =IF($B22="","",IFERROR(INDEX(Composicao_Fichas!$D:$D,SMALL(IF(Composicao_Fichas!$A$2:$A$500=$C$4,ROW(Composicao_Fichas!$A$2:$A$500)),11))&" "&INDEX(Composicao_Fichas!$E:$E,SMALL(IF(Composicao_Fichas!$A$2:$A$500=$C$4,ROW(Composicao_Fichas!$A$2:$A$500)),11)),"")) | E22: =IFERROR(INDEX(Composicao_Fichas!$H:$H,SMALL(IF(Composicao_Fichas!$A$2:$A$500=$C$4,ROW(Composicao_Fichas!$A$2:$A$500)),11)),"")
B23: =IFERROR(INDEX(Composicao_Fichas!$C:$C,SMALL(IF(Composicao_Fichas!$A$2:$A$500=$C$4,ROW(Composicao_Fichas!$A$2:$A$500)),12)),"") | D23: =IF($B23="","",IFERROR(INDEX(Composicao_Fichas!$D:$D,SMALL(IF(Composicao_Fichas!$A$2:$A$500=$C$4,ROW(Composicao_Fichas!$A$2:$A$500)),12))&" "&INDEX(Composicao_Fichas!$E:$E,SMALL(IF(Composicao_Fichas!$A$2:$A$500=$C$4,ROW(Composicao_Fichas!$A$2:$A$500)),12)),"")) | E23: =IFERROR(INDEX(Composicao_Fichas!$H:$H,SMALL(IF(Composicao_Fichas!$A$2:$A$500=$C$4,ROW(Composicao_Fichas!$A$2:$A$500)),12)),"")
B24: =IFERROR(INDEX(Composicao_Fichas!$C:$C,SMALL(IF(Composicao_Fichas!$A$2:$A$500=$C$4,ROW(Composicao_Fichas!$A$2:$A$500)),13)),"") | D24: =IF($B24="","",IFERROR(INDEX(Composicao_Fichas!$D:$D,SMALL(IF(Composicao_Fichas!$A$2:$A$500=$C$4,ROW(Composicao_Fichas!$A$2:$A$500)),13))&" "&INDEX(Composicao_Fichas!$E:$E,SMALL(IF(Composicao_Fichas!$A$2:$A$500=$C$4,ROW(Composicao_Fichas!$A$2:$A$500)),13)),"")) | E24: =IFERROR(INDEX(Composicao_Fichas!$H:$H,SMALL(IF(Composicao_Fichas!$A$2:$A$500=$C$4,ROW(Composicao_Fichas!$A$2:$A$500)),13)),"")
B25: =IFERROR(INDEX(Composicao_Fichas!$C:$C,SMALL(IF(Composicao_Fichas!$A$2:$A$500=$C$4,ROW(Composicao_Fichas!$A$2:$A$500)),14)),"") | D25: =IF($B25="","",IFERROR(INDEX(Composicao_Fichas!$D:$D,SMALL(IF(Composicao_Fichas!$A$2:$A$500=$C$4,ROW(Composicao_Fichas!$A$2:$A$500)),14))&" "&INDEX(Composicao_Fichas!$E:$E,SMALL(IF(Composicao_Fichas!$A$2:$A$500=$C$4,ROW(Composicao_Fichas!$A$2:$A$500)),14)),"")) | E25: =IFERROR(INDEX(Composicao_Fichas!$H:$H,SMALL(IF(Composicao_Fichas!$A$2:$A$500=$C$4,ROW(Composicao_Fichas!$A$2:$A$500)),14)),"")
B26: =IFERROR(INDEX(Composicao_Fichas!$C:$C,SMALL(IF(Composicao_Fichas!$A$2:$A$500=$C$4,ROW(Composicao_Fichas!$A$2:$A$500)),15)),"") | D26: =IF($B26="","",IFERROR(INDEX(Composicao_Fichas!$D:$D,SMALL(IF(Composicao_Fichas!$A$2:$A$500=$C$4,ROW(Composicao_Fichas!$A$2:$A$500)),15))&" "&INDEX(Composicao_Fichas!$E:$E,SMALL(IF(Composicao_Fichas!$A$2:$A$500=$C$4,ROW(Composicao_Fichas!$A$2:$A$500)),15)),"")) | E26: =IFERROR(INDEX(Composicao_Fichas!$H:$H,SMALL(IF(Composicao_Fichas!$A$2:$A$500=$C$4,ROW(Composicao_Fichas!$A$2:$A$500)),15)),"")
B27: =IFERROR(INDEX(Composicao_Fichas!$C:$C,SMALL(IF(Composicao_Fichas!$A$2:$A$500=$C$4,ROW(Composicao_Fichas!$A$2:$A$500)),16)),"") | D27: =IF($B27="","",IFERROR(INDEX(Composicao_Fichas!$D:$D,SMALL(IF(Composicao_Fichas!$A$2:$A$500=$C$4,ROW(Composicao_Fichas!$A$2:$A$500)),16))&" "&INDEX(Composicao_Fichas!$E:$E,SMALL(IF(Composicao_Fichas!$A$2:$A$500=$C$4,ROW(Composicao_Fichas!$A$2:$A$500)),16)),"")) | E27: =IFERROR(INDEX(Composicao_Fichas!$H:$H,SMALL(IF(Composicao_Fichas!$A$2:$A$500=$C$4,ROW(Composicao_Fichas!$A$2:$A$500)),16)),"")
B28: =IFERROR(INDEX(Composicao_Fichas!$C:$C,SMALL(IF(Composicao_Fichas!$A$2:$A$500=$C$4,ROW(Composicao_Fichas!$A$2:$A$500)),17)),"") | D28: =IF($B28="","",IFERROR(INDEX(Composicao_Fichas!$D:$D,SMALL(IF(Composicao_Fichas!$A$2:$A$500=$C$4,ROW(Composicao_Fichas!$A$2:$A$500)),17))&" "&INDEX(Composicao_Fichas!$E:$E,SMALL(IF(Composicao_Fichas!$A$2:$A$500=$C$4,ROW(Composicao_Fichas!$A$2:$A$500)),17)),"")) | E28: =IFERROR(INDEX(Composicao_Fichas!$H:$H,SMALL(IF(Composicao_Fichas!$A$2:$A$500=$C$4,ROW(Composicao_Fichas!$A$2:$A$500)),17)),"")
B29: =IFERROR(INDEX(Composicao_Fichas!$C:$C,SMALL(IF(Composicao_Fichas!$A$2:$A$500=$C$4,ROW(Composicao_Fichas!$A$2:$A$500)),18)),"") | D29: =IF($B29="","",IFERROR(INDEX(Composicao_Fichas!$D:$D,SMALL(IF(Composicao_Fichas!$A$2:$A$500=$C$4,ROW(Composicao_Fichas!$A$2:$A$500)),18))&" "&INDEX(Composicao_Fichas!$E:$E,SMALL(IF(Composicao_Fichas!$A$2:$A$500=$C$4,ROW(Composicao_Fichas!$A$2:$A$500)),18)),"")) | E29: =IFERROR(INDEX(Composicao_Fichas!$H:$H,SMALL(IF(Composicao_Fichas!$A$2:$A$500=$C$4,ROW(Composicao_Fichas!$A$2:$A$500)),18)),"")
B30: =IFERROR(INDEX(Composicao_Fichas!$C:$C,SMALL(IF(Composicao_Fichas!$A$2:$A$500=$C$4,ROW(Composicao_Fichas!$A$2:$A$500)),19)),"") | D30: =IF($B30="","",IFERROR(INDEX(Composicao_Fichas!$D:$D,SMALL(IF(Composicao_Fichas!$A$2:$A$500=$C$4,ROW(Composicao_Fichas!$A$2:$A$500)),19))&" "&INDEX(Composicao_Fichas!$E:$E,SMALL(IF(Composicao_Fichas!$A$2:$A$500=$C$4,ROW(Composicao_Fichas!$A$2:$A$500)),19)),"")) | E30: =IFERROR(INDEX(Composicao_Fichas!$H:$H,SMALL(IF(Composicao_Fichas!$A$2:$A$500=$C$4,ROW(Composicao_Fichas!$A$2:$A$500)),19)),"")
B31: =IFERROR(INDEX(Composicao_Fichas!$C:$C,SMALL(IF(Composicao_Fichas!$A$2:$A$500=$C$4,ROW(Composicao_Fichas!$A$2:$A$500)),20)),"") | D31: =IF($B31="","",IFERROR(INDEX(Composicao_Fichas!$D:$D,SMALL(IF(Composicao_Fichas!$A$2:$A$500=$C$4,ROW(Composicao_Fichas!$A$2:$A$500)),20))&" "&INDEX(Composicao_Fichas!$E:$E,SMALL(IF(Composicao_Fichas!$A$2:$A$500=$C$4,ROW(Composicao_Fichas!$A$2:$A$500)),20)),"")) | E31: =IFERROR(INDEX(Composicao_Fichas!$H:$H,SMALL(IF(Composicao_Fichas!$A$2:$A$500=$C$4,ROW(Composicao_Fichas!$A$2:$A$500)),20)),"")

Sheet _Validação
A1: ⚠️ VALIDAÇÃO — verifique antes de enviar
A3: Status | B3: Tipo | C3: Mensagem
A4: =IF(COUNTIFS(Insumos!F:F,"<=0",Insumos!A:A,"<>")>0,"🔴","✅") | B4: Erro | C4: ="Insumos sem preço: "&COUNTIFS(Insumos!F:F,"<=0",Insumos!A:A,"<>")&" (corrija na aba Insumos)"
A5: =IF(COUNTIFS(Preparos!C:C,"<=0",Preparos!A:A,"<>")>0,"🔴","✅") | B5: Erro | C5: ="Preparos sem rendimento: "&COUNTIFS(Preparos!C:C,"<=0",Preparos!A:A,"<>")&" (corrija na aba Preparos)"
A6: =IF(COUNTIFS(Fichas!C:C,"<=0",Fichas!A:A,"<>")>0,"🔴","✅") | B6: Erro | C6: ="Fichas sem preço de venda: "&COUNTIFS(Fichas!C:C,"<=0",Fichas!A:A,"<>")&" (corrija na aba Fichas)"
A7: =IF(SUMPRODUCT((Composicao_Preparos!C2:C500<>"")*(Composicao_Preparos!B2:B500=""))>0,"🔴","✅") | B7: Erro | C7: ="Comp_Preparos com Item não encontrado: "&SUMPRODUCT((Composicao_Preparos!C2:C500<>"")*(Composicao_Preparos!B2:B500=""))
A8: =IF(SUMPRODUCT((Composicao_Fichas!C2:C500<>"")*(Composicao_Fichas!B2:B500=""))>0,"🔴","✅") | B8: Erro | C8: ="Comp_Fichas com Item não encontrado: "&SUMPRODUCT((Composicao_Fichas!C2:C500<>"")*(Composicao_Fichas!B2:B500=""))
A9: =IF(SUMPRODUCT((Fichas!E2:E500<>"")*((Fichas!E2:E500<0.05)+(Fichas!E2:E500>0.7)))>0,"🟡","✅") | B9: Aviso | C9: ="Fichas com CMV impossível (<5% ou >70%): "&SUMPRODUCT((Fichas!E2:E500<>"")*((Fichas!E2:E500<0.05)+(Fichas!E2:E500>0.7)))
A10: =IF(SUMPRODUCT((Preparos!A2:A500<>"")*(COUNTIF(Composicao_Preparos!A:A,Preparos!A2:A500)=0))>0,"🟡","✅") | B10: Aviso | C10: ="Preparos sem composição: "&SUMPRODUCT((Preparos!A2:A500<>"")*(COUNTIF(Composicao_Preparos!A:A,Preparos!A2:A500)=0))
A11: =IF(SUMPRODUCT((Fichas!A2:A500<>"")*(COUNTIF(Composicao_Fichas!A:A,Fichas!A2:A500)=0))>0,"🟡","✅") | B11: Aviso | C11: ="Fichas sem composição: "&SUMPRODUCT((Fichas!A2:A500<>"")*(COUNTIF(Composicao_Fichas!A:A,Fichas!A2:A500)=0))
A14: ="Total: "&COUNTA(Insumos!A2:A500)&" insumos, "&COUNTA(Preparos!A2:A500)&" preparos, "&COUNTA(Fichas!A2:A500)&" fichas"
